Workbook

Sheet Data from Ocean
A1: 16 core blocks | B1: 591.8
A2: 2 additional cores | B2: 73.98
A4: client_id | B4: company_name | C4: service_id | D4: service_status | E4: os | F4: component | G4: integer_key | H4: cad_mrc | I4: cores | J4: 16 block | K4: 2 core add-ons | L4: Total cost to aptum | M4: Compatible 8/9? | N4: AM | O4: Churning | P4: Outreach | Q4: Discussion | R4: Notes | S4: Cody's Recommendation
A5: 7007654 | B5: Cenovus Energy Inc. | C5: 7516745 | D5: Online | E5: VMware ESXi 7.0 | F5: Intel Xeon E5-2620 v3 2.4 GHz 6 Cores 12 Threads 8 GT/s (w H/T) | G5: 38746789 | H5: 1815.28 | I5: =IFERROR(__xludf.DUMMYFUNCTION("IFERROR(VALUE(REGEXEXTRACT(F5, ""(\d+)[-\s]?Cores?"")))"),6.0) -> 6 | J5: =IF(I5>0, 1, "") -> 1 | K5: =IF(I5>0, MAX(0, I5-16)/2, "") -> 0 | L5: =J5*$B$1+K5*$B$2 -> 591.8 | M5: 7 | N5: Marko Andjelkovic | R5: Opportunity Created - CPQ Provided
A6: 7007654 | B6: Cenovus Energy Inc. | C6: 7516745 | D6: Online | E6: VMware ESXi 7.0 | F6: Intel Xeon E5-2620 v3 2.4 GHz 6 Cores 12 Threads 8 GT/s (w H/T) | G6: 38746790 | H6: 1815.28 | I6: =IFERROR(__xludf.DUMMYFUNCTION("IFERROR(VALUE(REGEXEXTRACT(F6, ""(\d+)[-\s]?Cores?"")))"),6.0) -> 6 | J6: =IF(I6>0, 1, "") -> 1 | K6: =IF(I6>0, MAX(0, I6-16)/2, "") -> 0 | L6: =J6*$B$1+K6*$B$2 -> 591.8 | M6: 7 | N6: Marko Andjelkovic | R6: Opportunity Created - CPQ Provided
A7: 7007654 | B7: Cenovus Energy Inc. | C7: 7516746 | D7: Online | E7: VMware ESXi 7.0 | F7: Intel Xeon E5-2620 v3 2.4 GHz 6 Cores 12 Threads 8 GT/s (w H/T) | G7: 38746809 | H7: 1815.28 | I7: =IFERROR(__xludf.DUMMYFUNCTION("IFERROR(VALUE(REGEXEXTRACT(F7, ""(\d+)[-\s]?Cores?"")))"),6.0) -> 6 | J7: =IF(I7>0, 1, "") -> 1 | K7: =IF(I7>0, MAX(0, I7-16)/2, "") -> 0 | L7: =J7*$B$1+K7*$B$2 -> 591.8 | M7: 7 | N7: Marko Andjelkovic | R7: Opportunity Created - CPQ Provided
A8: 7007654 | B8: Cenovus Energy Inc. | C8: 7516746 | D8: Online | E8: VMware ESXi 7.0 | F8: Intel Xeon E5-2620 v3 2.4 GHz 6 Cores 12 Threads 8 GT/s (w H/T) | G8: 38746810 | H8: 1815.28 | I8: =IFERROR(__xludf.DUMMYFUNCTION("IFERROR(VALUE(REGEXEXTRACT(F8, ""(\d+)[-\s]?Cores?"")))"),6.0) -> 6 | J8: =IF(I8>0, 1, "") -> 1 | K8: =IF(I8>0, MAX(0, I8-16)/2, "") -> 0 | L8: =J8*$B$1+K8*$B$2 -> 591.8 | M8: 7 | N8: Marko Andjelkovic | R8: Opportunity Created - CPQ Provided
A9: 7012926 | B9: Currencies Direct Ltd | C9: 4968897 | D9: Online | E9: VMware ESXi 6.0 | F9: Intel Xeon E5-2630 v3 2.4 GHz 8-Core 16 Threads (w H/T) | G9: 14710440 | H9: 2435.2472 | I9: =IFERROR(__xludf.DUMMYFUNCTION("IFERROR(VALUE(REGEXEXTRACT(F9, ""(\d+)[-\s]?Cores?"")))"),8.0) -> 8 | J9: =IF(I9>0, 1, "") -> 1 | K9: =IF(I9>0, MAX(0, I9-16)/2, "") -> 0 | L9: =J9*$B$1+K9*$B$2 -> 591.8 | M9: 7 | N9: Jennifer Wilson | Q9: x | R9: Opportunity Created - CPQ Provided
A10: 7012926 | B10: Currencies Direct Ltd | C10: 4968897 | D10: Online | E10: VMware ESXi 6.0 | F10: Intel Xeon E5-2630 v3 2.4 GHz 8-Core 16 Threads (w H/T) | G10: 14710441 | H10: 2435.2472 | I10: =IFERROR(__xludf.DUMMYFUNCTION("IFERROR(VALUE(REGEXEXTRACT(F10, ""(\d+)[-\s]?Cores?"")))"),8.0) -> 8 | J10: =IF(I10>0, 1, "") -> 1 | K10: =IF(I10>0, MAX(0, I10-16)/2, "") -> 0 | L10: =J10*$B$1+K10*$B$2 -> 591.8 | M10: 7 | N10: Jennifer Wilson | Q10: x | R10: Opportunity Created - CPQ Provided
A11: 7012926 | B11: Currencies Direct Ltd | C11: 4968898 | D11: Online | E11: VMware ESXi 6.0 | F11: Intel Xeon E5-2630 v3 2.4 GHz 8-Core 16 Threads (w H/T) | G11: 14710466 | H11: 2435.2472 | I11: =IFERROR(__xludf.DUMMYFUNCTION("IFERROR(VALUE(REGEXEXTRACT(F11, ""(\d+)[-\s]?Cores?"")))"),8.0) -> 8 | J11: =IF(I11>0, 1, "") -> 1 | K11: =IF(I11>0, MAX(0, I11-16)/2, "") -> 0 | L11: =J11*$B$1+K11*$B$2 -> 591.8 | M11: 7 | N11: Jennifer Wilson | Q11: x | R11: Opportunity Created - CPQ Provided
A12: 7012926 | B12: Currencies Direct Ltd | C12: 4968898 | D12: Online | E12: VMware ESXi 6.0 | F12: Intel Xeon E5-2630 v3 2.4 GHz 8-Core 16 Threads (w H/T) | G12: 14710467 | H12: 2435.2472 | I12: =IFERROR(__xludf.DUMMYFUNCTION("IFERROR(VALUE(REGEXEXTRACT(F12, ""(\d+)[-\s]?Cores?"")))"),8.0) -> 8 | J12: =IF(I12>0, 1, "") -> 1 | K12: =IF(I12>0, MAX(0, I12-16)/2, "") -> 0 | L12: =J12*$B$1+K12*$B$2 -> 591.8 | M12: 7 | N12: Jennifer Wilson | Q12: x | R12: Opportunity Created - CPQ Provided
A13: 7013453 | B13: 20-20 Technologies inc. | C13: 7337052 | D13: Online | E13: VMware ESXi 7.0 | F13: Intel Xeon E5-2630 v3 2.4 GHz 8-Core 16 Threads (w H/T) | G13: 36777479 | H13: 3437.57 | I13: =IFERROR(__xludf.DUMMYFUNCTION("IFERROR(VALUE(REGEXEXTRACT(F13, ""(\d+)[-\s]?Cores?"")))"),8.0) -> 8 | J13: =IF(I13>0, 1, "") -> 1 | K13: =IF(I13>0, MAX(0, I13-16)/2, "") -> 0 | L13: =J13*$B$1+K13*$B$2 -> 591.8 | M13: 7 | N13: Roland Gonzales | O13: Churning | Q13: No action
A14: 7013453 | B14: 20-20 Technologies inc. | C14: 7337052 | D14: Online | E14: VMware ESXi 7.0 | F14: Intel Xeon E5-2630 v3 2.4 GHz 8-Core 16 Threads (w H/T) | G14: 36777480 | H14: 3437.57 | I14: =IFERROR(__xludf.DUMMYFUNCTION("IFERROR(VALUE(REGEXEXTRACT(F14, ""(\d+)[-\s]?Cores?"")))"),8.0) -> 8 | J14: =IF(I14>0, 1, "") -> 1 | K14: =IF(I14>0, MAX(0, I14-16)/2, "") -> 0 | L14: =J14*$B$1+K14*$B$2 -> 591.8 | M14: 7 | N14: Roland Gonzales | O14: Churning | Q14: No action
A15: 7013453 | B15: 20-20 Technologies inc. | C15: 7337053 | D15: Online | E15: VMware ESXi 7.0 | F15: Intel Xeon E5-2630 v3 2.4 GHz 8-Core 16 Threads (w H/T) | G15: 36777503 | H15: 3437.57 | I15: =IFERROR(__xludf.DUMMYFUNCTION("IFERROR(VALUE(REGEXEXTRACT(F15, ""(\d+)[-\s]?Cores?"")))"),8.0) -> 8 | J15: =IF(I15>0, 1, "") -> 1 | K15: =IF(I15>0, MAX(0, I15-16)/2, "") -> 0 | L15: =J15*$B$1+K15*$B$2 -> 591.8 | M15: 7 | N15: Roland Gonzales | O15: Churning | Q15: No action
A16: 7013453 | B16: 20-20 Technologies inc. | C16: 7337053 | D16: Online | E16: VMware ESXi 7.0 | F16: Intel Xeon E5-2630 v3 2.4 GHz 8-Core 16 Threads (w H/T) | G16: 36777504 | H16: 3437.57 | I16: =IFERROR(__xludf.DUMMYFUNCTION("IFERROR(VALUE(REGEXEXTRACT(F16, ""(\d+)[-\s]?Cores?"")))"),8.0) -> 8 | J16: =IF(I16>0, 1, "") -> 1 | K16: =IF(I16>0, MAX(0, I16-16)/2, "") -> 0 | L16: =J16*$B$1+K16*$B$2 -> 591.8 | M16: 7 | N16: Roland Gonzales | O16: Churning | Q16: No action
A17: 1000343 | B17: Internet Edge Solutions Inc. | C17: 7524554 | D17: Online | E17: VMware ESXi 7.0 | F17: Intel Xeon E5-2630 v3 2.4 GHz 8-Core 16 Threads (w H/T) | G17: 38863703 | H17: 1667.63 | I17: =IFERROR(__xludf.DUMMYFUNCTION("IFERROR(VALUE(REGEXEXTRACT(F17, ""(\d+)[-\s]?Cores?"")))"),8.0) -> 8 | J17: =IF(I17>0, 1, "") -> 1 | K17: =IF(I17>0, MAX(0, I17-16)/2, "") -> 0 | L17: =J17*$B$1+K17*$B$2 -> 591.8 | M17: 7 | N17: Roland Gonzales | Q17: 10/6/25 sent recommendation for side-by-side migration to single CPU vHosts. Wait for customer decision. | R17: Opportunity Created - CPQ Provided
A18: 1000343 | B18: Internet Edge Solutions Inc. | C18: 7524554 | D18: Online | E18: VMware ESXi 7.0 | F18: Intel Xeon E5-2630 v3 2.4 GHz 8-Core 16 Threads (w H/T) | G18: 38863704 | H18: 1667.63 | I18: =IFERROR(__xludf.DUMMYFUNCTION("IFERROR(VALUE(REGEXEXTRACT(F18, ""(\d+)[-\s]?Cores?"")))"),8.0) -> 8 | J18: =IF(I18>0, 1, "") -> 1 | K18: =IF(I18>0, MAX(0, I18-16)/2, "") -> 0 | L18: =J18*$B$1+K18*$B$2 -> 591.8 | M18: 7 | N18: Roland Gonzales | Q18: 10/6/25 sent recommendation for side-by-side migration to single CPU vHosts. Wait for customer decision. | R18: Opportunity Created - CPQ Provided
A19: 1000343 | B19: Internet Edge Solutions Inc. | C19: 7524555 | D19: Online | E19: VMware ESXi 7.0 | F19: Intel Xeon E5-2630 v3 2.4 GHz 8-Core 16 Threads (w H/T) | G19: 38863722 | H19: 1667.63 | I19: =IFERROR(__xludf.DUMMYFUNCTION("IFERROR(VALUE(REGEXEXTRACT(F19, ""(\d+)[-\s]?Cores?"")))"),8.0) -> 8 | J19: =IF(I19>0, 1, "") -> 1 | K19: =IF(I19>0, MAX(0, I19-16)/2, "") -> 0 | L19: =J19*$B$1+K19*$B$2 -> 591.8 | M19: 7 | N19: Roland Gonzales | Q19: 10/6/25 sent recommendation for side-by-side migration to single CPU vHosts. Wait for customer decision. | R19: Opportunity Created - CPQ Provided
A20: 1000343 | B20: Internet Edge Solutions Inc. | C20: 7524555 | D20: Online | E20: VMware ESXi 7.0 | F20: Intel Xeon E5-2630 v3 2.4 GHz 8-Core 16 Threads (w H/T) | G20: 38863723 | H20: 1667.63 | I20: =IFERROR(__xludf.DUMMYFUNCTION("IFERROR(VALUE(REGEXEXTRACT(F20, ""(\d+)[-\s]?Cores?"")))"),8.0) -> 8 | J20: =IF(I20>0, 1, "") -> 1 | K20: =IF(I20>0, MAX(0, I20-16)/2, "") -> 0 | L20: =J20*$B$1+K20*$B$2 -> 591.8 | M20: 7 | N20: Roland Gonzales | Q20: 10/6/25 sent recommendation for side-by-side migration to single CPU vHosts. Wait for customer decision. | R20: Opportunity Created - CPQ Provided
A21: 7003351 | B21: ENTREGAS PUNTUALES S DE RL DE CV | C21: 6229696 | D21: moved | E21: VMware ESXi 6.5 | F21: Default Intel Xeon Silver 4110 2.1 GHz 8 Cores/16T (85W TDP) | G21: 26065420 | H21: 1688.1514 | I21: =IFERROR(__xludf.DUMMYFUNCTION("IFERROR(VALUE(REGEXEXTRACT(F21, ""(\d+)[-\s]?Cores?"")))"),8.0) -> 8 | J21: =IF(I21>0, 1, "") -> 1 | K21: =IF(I21>0, MAX(0, I21-16)/2, "") -> 0 | L21: =J21*$B$1+K21*$B$2 -> 591.8 | M21: 7,8 | N21: Elizabeth Perez | P21: Done | Q21: x | R21: Migrating to newest version
A22: 7003351 | B22: ENTREGAS PUNTUALES S DE RL DE CV | C22: 6229696 | D22: moved | E22: VMware ESXi 6.5 | F22: Intel Xeon 4110 or 4208 2.1 GHz 8 Cores/16T (85W TDP) | G22: 39308698 | H22: 1688.1514 | I22: =IFERROR(__xludf.DUMMYFUNCTION("IFERROR(VALUE(REGEXEXTRACT(F22, ""(\d+)[-\s]?Cores?"")))"),8.0) -> 8 | J22: =IF(I22>0, 1, "") -> 1 | K22: =IF(I22>0, MAX(0, I22-16)/2, "") -> 0 | L22: =J22*$B$1+K22*$B$2 -> 591.8 | M22: 7,8 | N22: Elizabeth Perez | P22: Done | Q22: x | R22: Migrating to newest version
A23: 7008621 | B23: Premia Solutions Limited | C23: 6819536 | D23: Online | E23: VMware ESXi 7.0 | F23: Default Intel Xeon 4110/4208 2.1 GHz 8 Core/16T (85W TDP) | G23: 31059001 | H23: 3174.929 | I23: =IFERROR(__xludf.DUMMYFUNCTION("IFERROR(VALUE(REGEXEXTRACT(F23, ""(\d+)[-\s]?Cores?"")))"),8.0) -> 8 | J23: =IF(I23>0, 1, "") -> 1 | K23: =IF(I23>0, MAX(0, I23-16)/2, "") -> 0 | L23: =J23*$B$1+K23*$B$2 -> 591.8 | M23: 7,8 | N23: Darren Wells | O23: Azure Migration | P23: Weekly | R23: Ongoing Azure Migration Project
A24: 7008621 | B24: Premia Solutions Limited | C24: 6819536 | D24: Online | E24: VMware ESXi 7.0 | F24: Intel Xeon 4110 or 4208 2.1 GHz 8 Cores/16T (85W TDP) | G24: 31059006 | H24: 3174.929 | I24: =IFERROR(__xludf.DUMMYFUNCTION("IFERROR(VALUE(REGEXEXTRACT(F24, ""(\d+)[-\s]?Cores?"")))"),8.0) -> 8 | J24: =IF(I24>0, 1, "") -> 1 | K24: =IF(I24>0, MAX(0, I24-16)/2, "") -> 0 | L24: =J24*$B$1+K24*$B$2 -> 591.8 | M24: 7,8 | N24: Darren Wells | O24: Azure Migration | P24: Weekly | R24: Ongoing Azure Migration Project
A25: 7008621 | B25: Premia Solutions Limited | C25: 6819537 | D25: Online | E25: VMware ESXi 7.0 | F25: Default Intel Xeon 4110/4208 2.1 GHz 8 Core/16T (85W TDP) | G25: 31059024 | H25: 3174.929 | I25: =IFERROR(__xludf.DUMMYFUNCTION("IFERROR(VALUE(REGEXEXTRACT(F25, ""(\d+)[-\s]?Cores?"")))"),8.0) -> 8 | J25: =IF(I25>0, 1, "") -> 1 | K25: =IF(I25>0, MAX(0, I25-16)/2, "") -> 0 | L25: =J25*$B$1+K25*$B$2 -> 591.8 | M25: 7,8 | N25: Darren Wells | O25: Azure Migration | P25: Weekly | R25: Ongoing Azure Migration Project
A26: 7008621 | B26: Premia Solutions Limited | C26: 6819537 | D26: Online | E26: VMware ESXi 7.0 | F26: Intel Xeon 4110 or 4208 2.1 GHz 8 Cores/16T (85W TDP) | G26: 31059029 | H26: 3174.929 | I26: =IFERROR(__xludf.DUMMYFUNCTION("IFERROR(VALUE(REGEXEXTRACT(F26, ""(\d+)[-\s]?Cores?"")))"),8.0) -> 8 | J26: =IF(I26>0, 1, "") -> 1 | K26: =IF(I26>0, MAX(0, I26-16)/2, "") -> 0 | L26: =J26*$B$1+K26*$B$2 -> 591.8 | M26: 7,8 | N26: Darren Wells | O26: Azure Migration | P26: Weekly | R26: Ongoing Azure Migration Project
A27: 7015128 | B27: Interpro Technology Solutions Limited | C27: 6819554 | D27: WinBack | E27: VMware ESXi 7.0 | F27: Default Intel Xeon 4110/4208 2.1 GHz 8 Core/16T (85W TDP) | G27: 31061538 | H27: 2333.4095 | I27: =IFERROR(__xludf.DUMMYFUNCTION("IFERROR(VALUE(REGEXEXTRACT(F27, ""(\d+)[-\s]?Cores?"")))"),8.0) -> 8 | J27: =IF(I27>0, 1, "") -> 1 | K27: =IF(I27>0, MAX(0, I27-16)/2, "") -> 0 | L27: =J27*$B$1+K27*$B$2 -> 591.8 | M27: 7,8 | N27: Jennifer Wilson | O27: Churning? | R27: Services being cancelled
A28: 7015128 | B28: Interpro Technology Solutions Limited | C28: 6819554 | D28: WinBack | E28: VMware ESXi 7.0 | F28: Intel Xeon 4110 or 4208 2.1 GHz 8 Cores/16T (85W TDP) | G28: 31061555 | H28: 2333.4095 | I28: =IFERROR(__xludf.DUMMYFUNCTION("IFERROR(VALUE(REGEXEXTRACT(F28, ""(\d+)[-\s]?Cores?"")))"),8.0) -> 8 | J28: =IF(I28>0, 1, "") -> 1 | K28: =IF(I28>0, MAX(0, I28-16)/2, "") -> 0 | L28: =J28*$B$1+K28*$B$2 -> 591.8 | M28: 7,8 | N28: Jennifer Wilson | O28: Churning? | R28: Services being cancelled
A29: 7015128 | B29: Interpro Technology Solutions Limited | C29: 6819555 | D29: WinBack | E29: VMware ESXi 8.0 | F29: Default Intel Xeon 4110/4208 2.1 GHz 8 Core/16T (85W TDP) | G29: 31061570 | H29: 2333.4095 | I29: =IFERROR(__xludf.DUMMYFUNCTION("IFERROR(VALUE(REGEXEXTRACT(F29, ""(\d+)[-\s]?Cores?"")))"),8.0) -> 8 | J29: =IF(I29>0, 1, "") -> 1 | K29: =IF(I29>0, MAX(0, I29-16)/2, "") -> 0 | L29: =J29*$B$1+K29*$B$2 -> 591.8 | M29: 7,8 | N29: Jennifer Wilson | O29: Churning? | R29: Services being cancelled
A30: 7015128 | B30: Interpro Technology Solutions Limited | C30: 6819555 | D30: WinBack | E30: VMware ESXi 8.0 | F30: Intel Xeon 4110 or 4208 2.1 GHz 8 Cores/16T (85W TDP) | G30: 31061587 | H30: 2333.4095 | I30: =IFERROR(__xludf.DUMMYFUNCTION("IFERROR(VALUE(REGEXEXTRACT(F30, ""(\d+)[-\s]?Cores?"")))"),8.0) -> 8 | J30: =IF(I30>0, 1, "") -> 1 | K30: =IF(I30>0, MAX(0, I30-16)/2, "") -> 0 | L30: =J30*$B$1+K30*$B$2 -> 591.8 | M30: 7,8 | N30: Jennifer Wilson | O30: Churning? | R30: Services being cancelled
A31: 7007499 | B31: Nomad Digital Inc. | C31: 7290376 | D31: Online | E31: VMware ESXi 6.5 | F31: Default Intel Xeon 4110/4208 2.1 GHz 8 Core/16T (85W TDP) | G31: 36125133 | H31: 3771.8909 | I31: =IFERROR(__xludf.DUMMYFUNCTION("IFERROR(VALUE(REGEXEXTRACT(F31, ""(\d+)[-\s]?Cores?"")))"),8.0) -> 8 | J31: =IF(I31>0, 1, "") -> 1 | K31: =IF(I31>0, MAX(0, I31-16)/2, "") -> 0 | L31: =J31*$B$1+K31*$B$2 -> 591.8 | M31: 7,8 | N31: Jennifer Wilson | Q31: x | R31: Opportunity Created - CPQ Provided
A32: 7007499 | B32: Nomad Digital Inc. | C32: 7290377 | D32: Online | E32: VMware ESXi 6.5 | F32: Default Intel Xeon 4110/4208 2.1 GHz 8 Core/16T (85W TDP) | G32: 36125163 | H32: 3771.8909 | I32: =IFERROR(__xludf.DUMMYFUNCTION("IFERROR(VALUE(REGEXEXTRACT(F32, ""(\d+)[-\s]?Cores?"")))"),8.0) -> 8 | J32: =IF(I32>0, 1, "") -> 1 | K32: =IF(I32>0, MAX(0, I32-16)/2, "") -> 0 | L32: =J32*$B$1+K32*$B$2 -> 591.8 | M32: 7,8 | N32: Jennifer Wilson | Q32: x | R32: Opportunity Created - CPQ Provided
A33: 5960514 | B33: ViOptix, Inc. - PO # 1357 | C33: 7337070 | D33: Online | E33: VMware ESXi 7.0 | F33: Default Intel Xeon 4110/4208 2.1 GHz 8 Core/16T (85W TDP) | G33: 36777581 | H33: 1039.2525 | I33: =IFERROR(__xludf.DUMMYFUNCTION("IFERROR(VALUE(REGEXEXTRACT(F33, ""(\d+)[-\s]?Cores?"")))"),8.0) -> 8 | J33: =IF(I33>0, 1, "") -> 1 | K33: =IF(I33>0, MAX(0, I33-16)/2, "") -> 0 | L33: =J33*$B$1+K33*$B$2 -> 591.8 | M33: 7,8 | N33: Roger Gonzales | Q33: x | R33: Working on a hw refresh that would address this
A34: 5960514 | B34: ViOptix, Inc. - PO # 1357 | C34: 7337071 | D34: Online | E34: VMware ESXi 7.0 | F34: Default Intel Xeon 4110/4208 2.1 GHz 8 Core/16T (85W TDP) | G34: 36777610 | H34: 1039.2525 | I34: =IFERROR(__xludf.DUMMYFUNCTION("IFERROR(VALUE(REGEXEXTRACT(F34, ""(\d+)[-\s]?Cores?"")))"),8.0) -> 8 | J34: =IF(I34>0, 1, "") -> 1 | K34: =IF(I34>0, MAX(0, I34-16)/2, "") -> 0 | L34: =J34*$B$1+K34*$B$2 -> 591.8 | M34: 7,8 | N34: Roger Gonzales | Q34: x | R34: Working on a hw refresh that would address this
A35: 7014318 | B35: BCOM 2000 HOLDINGS PTY LTD | C35: 7456977 | D35: Online | E35: VMware ESXi 7.0 | F35: Default Intel Xeon 4110/4208 2.1 GHz 8 Core/16T (85W TDP) | G35: 37851619 | H35: 2494.3512 | I35: =IFERROR(__xludf.DUMMYFUNCTION("IFERROR(VALUE(REGEXEXTRACT(F35, ""(\d+)[-\s]?Cores?"")))"),8.0) -> 8 | J35: =IF(I35>0, 1, "") -> 1 | K35: =IF(I35>0, MAX(0, I35-16)/2, "") -> 0 | L35: =J35*$B$1+K35*$B$2 -> 591.8 | M35: 7,8 | N35: Jennifer Wilson | Q35: x | R35: Working on a hw refresh that would address this
A36: 7014318 | B36: BCOM 2000 HOLDINGS PTY LTD | C36: 7456977 | D36: Online | E36: VMware ESXi 7.0 | F36: Intel Xeon 4110 or 4208 2.1 GHz 8 Cores/16T (85W TDP) | G36: 37851631 | H36: 2494.3512 | I36: =IFERROR(__xludf.DUMMYFUNCTION("IFERROR(VALUE(REGEXEXTRACT(F36, ""(\d+)[-\s]?Cores?"")))"),8.0) -> 8 | J36: =IF(I36>0, 1, "") -> 1 | K36: =IF(I36>0, MAX(0, I36-16)/2, "") -> 0 | L36: =J36*$B$1+K36*$B$2 -> 591.8 | M36: 7,8 | N36: Jennifer Wilson | Q36: x | R36: Working on a hw refresh that would address this
A37: 7014791 | B37: Chestnut Health System, Inc. | C37: 7730302 | D37: Online | E37: VMware ESXi 7.0 | F37: Default Intel Xeon 4110/4208 2.1 GHz 8 Core/16T (85W TDP) | G37: 42189459 | H37: 1753.9136 | I37: =IFERROR(__xludf.DUMMYFUNCTION("IFERROR(VALUE(REGEXEXTRACT(F37, ""(\d+)[-\s]?Cores?"")))"),8.0) -> 8 | J37: =IF(I37>0, 1, "") -> 1 | K37: =IF(I37>0, MAX(0, I37-16)/2, "") -> 0 | L37: =J37*$B$1+K37*$B$2 -> 591.8 | M37: 7,8 | N37: Roland Gonzales | O37: Atlanta | Q37: 10/7 DD approved, reviewed side-by-side migration with Matt Winn. He likes this approach for both MIA and ATL - sent him proposal. He will review with Barb and get back to us on term. 10/6/25 waiting for DD approval for Miami and mirror in ATL - Gary confirmed there is enough resources to do in place upgrade | R37: Opportunity Created - waiting on Cody's recos
A38: 7014791 | B38: Chestnut Health System, Inc. | C38: 7730302 | D38: Online | E38: VMware ESXi 7.0 | F38: Intel Xeon 4110 or 4208 2.1 GHz 8 Cores/16T (85W TDP) | G38: 42189463 | H38: 1753.9136 | I38: =IFERROR(__xludf.DUMMYFUNCTION("IFERROR(VALUE(REGEXEXTRACT(F38, ""(\d+)[-\s]?Cores?"")))"),8.0) -> 8 | J38: =IF(I38>0, 1, "") -> 1 | K38: =IF(I38>0, MAX(0, I38-16)/2, "") -> 0 | L38: =J38*$B$1+K38*$B$2 -> 591.8 | M38: 7,8 | N38: Roland Gonzales | O38: Atlanta | Q38: 10/7 DD approved, reviewed side-by-side migration with Matt Winn. He likes this approach for both MIA and ATL - sent him proposal. He will review with Barb and get back to us on term. 10/6/25 waiting for DD approval for Miami and mirror in ATL - Gary confirmed there is enough resources to do in place upgrade | R38: Opportunity Created - waiting on Cody's recos
A39: 7014791 | B39: Chestnut Health System, Inc. | C39: 7730303 | D39: Online | E39: VMware ESXi 7.0 | F39: Default Intel Xeon 4110/4208 2.1 GHz 8 Core/16T (85W TDP) | G39: 42189482 | H39: 1782.0472 | I39: =IFERROR(__xludf.DUMMYFUNCTION("IFERROR(VALUE(REGEXEXTRACT(F39, ""(\d+)[-\s]?Cores?"")))"),8.0) -> 8 | J39: =IF(I39>0, 1, "") -> 1 | K39: =IF(I39>0, MAX(0, I39-16)/2, "") -> 0 | L39: =J39*$B$1+K39*$B$2 -> 591.8 | M39: 7,8 | N39: Roland Gonzales | O39: Atlanta | Q39: 10/7 DD approved, reviewed side-by-side migration with Matt Winn. He likes this approach for both MIA and ATL - sent him proposal. He will review with Barb and get back to us on term. 10/6/25 waiting for DD approval for Miami and mirror in ATL - Gary confirmed there is enough resources to do in place upgrade | R39: Opportunity Created - waiting on Cody's recos
A40: 7014791 | B40: Chestnut Health System, Inc. | C40: 7730303 | D40: Online | E40: VMware ESXi 7.0 | F40: Intel Xeon 4110 or 4208 2.1 GHz 8 Cores/16T (85W TDP) | G40: 42189486 | H40: 1782.0472 | I40: =IFERROR(__xludf.DUMMYFUNCTION("IFERROR(VALUE(REGEXEXTRACT(F40, ""(\d+)[-\s]?Cores?"")))"),8.0) -> 8 | J40: =IF(I40>0, 1, "") -> 1 | K40: =IF(I40>0, MAX(0, I40-16)/2, "") -> 0 | L40: =J40*$B$1+K40*$B$2 -> 591.8 | M40: 7,8 | N40: Roland Gonzales | O40: Atlanta | Q40: 10/7 DD approved, reviewed side-by-side migration with Matt Winn. He likes this approach for both MIA and ATL - sent him proposal. He will review with Barb and get back to us on term. 10/6/25 waiting for DD approval for Miami and mirror in ATL - Gary confirmed there is enough resources to do in place upgrade | R40: Opportunity Created - waiting on Cody's recos
A41: 5711523 | B41: Global Maritime Transportation Services, Inc. | C41: 7750604 | D41: Online | E41: VMware ESXi 7.0 | F41: Default Intel Xeon 4110/4208 2.1 GHz 8 Core/16T (85W TDP) | G41: 42498421 | H41: 2893.1081 | I41: =IFERROR(__xludf.DUMMYFUNCTION("IFERROR(VALUE(REGEXEXTRACT(F41, ""(\d+)[-\s]?Cores?"")))"),8.0) -> 8 | J41: =IF(I41>0, 1, "") -> 1 | K41: =IF(I41>0, MAX(0, I41-16)/2, "") -> 0 | L41: =J41*$B$1+K41*$B$2 -> 591.8 | M41: 7,8 | N41: Roger Gonzales
A42: 5711523 | B42: Global Maritime Transportation Services, Inc. | C42: 7750604 | D42: Online | E42: VMware ESXi 7.0 | F42: Default Intel Xeon 4110/4208 2.1 GHz 8 Core/16T (85W TDP) | G42: 42498422 | H42: 2893.1081 | I42: =IFERROR(__xludf.DUMMYFUNCTION("IFERROR(VALUE(REGEXEXTRACT(F42, ""(\d+)[-\s]?Cores?"")))"),8.0) -> 8 | J42: =IF(I42>0, 1, "") -> 1 | K42: =IF(I42>0, MAX(0, I42-16)/2, "") -> 0 | L42: =J42*$B$1+K42*$B$2 -> 591.8 | M42: 7,8 | N42: Roger Gonzales
A43: 5711523 | B43: Global Maritime Transportation Services, Inc. | C43: 7750605 | D43: Online | E43: VMware ESXi 7.0 | F43: Default Intel Xeon 4110/4208 2.1 GHz 8 Core/16T (85W TDP) | G43: 42498441 | H43: 2893.1081 | I43: =IFERROR(__xludf.DUMMYFUNCTION("IFERROR(VALUE(REGEXEXTRACT(F43, ""(\d+)[-\s]?Cores?"")))"),8.0) -> 8 | J43: =IF(I43>0, 1, "") -> 1 | K43: =IF(I43>0, MAX(0, I43-16)/2, "") -> 0 | L43: =J43*$B$1+K43*$B$2 -> 591.8 | M43: 7,8 | N43: Roger Gonzales
A44: 5711523 | B44: Global Maritime Transportation Services, Inc. | C44: 7750605 | D44: Online | E44: VMware ESXi 7.0 | F44: Default Intel Xeon 4110/4208 2.1 GHz 8 Core/16T (85W TDP) | G44: 42498442 | H44: 2893.1081 | I44: =IFERROR(__xludf.DUMMYFUNCTION("IFERROR(VALUE(REGEXEXTRACT(F44, ""(\d+)[-\s]?Cores?"")))"),8.0) -> 8 | J44: =IF(I44>0, 1, "") -> 1 | K44: =IF(I44>0, MAX(0, I44-16)/2, "") -> 0 | L44: =J44*$B$1+K44*$B$2 -> 591.8 | M44: 7,8 | N44: Roger Gonzales
A45: 7014870 | B45: Currency Stream International Limited | C45: 7750639 | D45: Online | E45: VMware ESXi 7.0 | F45: Default Intel Xeon 4110/4208 2.1 GHz 8 Core/16T (85W TDP) | G45: 42503462 | H45: 3368.1743 | I45: =IFERROR(__xludf.DUMMYFUNCTION("IFERROR(VALUE(REGEXEXTRACT(F45, ""(\d+)[-\s]?Cores?"")))"),8.0) -> 8 | J45: =IF(I45>0, 1, "") -> 1 | K45: =IF(I45>0, MAX(0, I45-16)/2, "") -> 0 | L45: =J45*$B$1+K45*$B$2 -> 591.8 | M45: 7,8 | N45: Jennifer Wilson | Q45: x | R45: TAM Leading VMware project - Opp created
A46: 7014870 | B46: Currency Stream International Limited | C46: 7750639 | D46: Online | E46: VMware ESXi 7.0 | F46: Intel Xeon 4110 or 4208 2.1 GHz 8 Cores/16T (85W TDP) | G46: 42503467 | H46: 3368.1743 | I46: =IFERROR(__xludf.DUMMYFUNCTION("IFERROR(VALUE(REGEXEXTRACT(F46, ""(\d+)[-\s]?Cores?"")))"),8.0) -> 8 | J46: =IF(I46>0, 1, "") -> 1 | K46: =IF(I46>0, MAX(0, I46-16)/2, "") -> 0 | L46: =J46*$B$1+K46*$B$2 -> 591.8 | M46: 7,8 | N46: Jennifer Wilson | Q46: x | R46: TAM Leading VMware project - Opp created
A47: 7014870 | B47: Currency Stream International Limited | C47: 7750640 | D47: Online | E47: VMware ESXi 7.0 | F47: Default Intel Xeon 4110/4208 2.1 GHz 8 Core/16T (85W TDP) | G47: 42503487 | H47: 3368.1743 | I47: =IFERROR(__xludf.DUMMYFUNCTION("IFERROR(VALUE(REGEXEXTRACT(F47, ""(\d+)[-\s]?Cores?"")))"),8.0) -> 8 | J47: =IF(I47>0, 1, "") -> 1 | K47: =IF(I47>0, MAX(0, I47-16)/2, "") -> 0 | L47: =J47*$B$1+K47*$B$2 -> 591.8 | M47: 7,8 | N47: Jennifer Wilson | Q47: x | R47: TAM Leading VMware project - Opp created
A48: 7014870 | B48: Currency Stream International Limited | C48: 7750640 | D48: Online | E48: VMware ESXi 7.0 | F48: Intel Xeon 4110 or 4208 2.1 GHz 8 Cores/16T (85W TDP) | G48: 42503492 | H48: 3368.1743 | I48: =IFERROR(__xludf.DUMMYFUNCTION("IFERROR(VALUE(REGEXEXTRACT(F48, ""(\d+)[-\s]?Cores?"")))"),8.0) -> 8 | J48: =IF(I48>0, 1, "") -> 1 | K48: =IF(I48>0, MAX(0, I48-16)/2, "") -> 0 | L48: =J48*$B$1+K48*$B$2 -> 591.8 | M48: 7,8 | N48: Jennifer Wilson | Q48: x | R48: TAM Leading VMware project - Opp created
A49: 7003351 | B49: ENTREGAS PUNTUALES S DE RL DE CV | C49: 7931593 | D49: Provision | E49: VMware ESXi 8.0 | F49: Default Intel Xeon 4110/4208 2.1 GHz 8 Core/16T (85W TDP) | G49: 43708238 | H49: 1688.1514 | I49: =IFERROR(__xludf.DUMMYFUNCTION("IFERROR(VALUE(REGEXEXTRACT(F49, ""(\d+)[-\s]?Cores?"")))"),8.0) -> 8 | J49: =IF(I49>0, 1, "") -> 1 | K49: =IF(I49>0, MAX(0, I49-16)/2, "") -> 0 | L49: =J49*$B$1+K49*$B$2 -> 591.8 | M49: 7,8 | N49: Elizabeth Perez | P49: Done | R49: In Provision, see column D
A50: 7014638 | B50: HYTECK, SA d/b/a AROMA ZONE | C50: 6483387 | D50: Online | E50: VMware ESXi 7.0 | F50: Intel Xeon E5-2650 v4 2.2 GHz 12 Cores 24 Thrds 9.6 GT/s (w H/T) | G50: 28132866 | H50: 2661.6242 | I50: =IFERROR(__xludf.DUMMYFUNCTION("IFERROR(VALUE(REGEXEXTRACT(F50, ""(\d+)[-\s]?Cores?"")))"),12.0) -> 12 | J50: =IF(I50>0, 1, "") -> 1 | K50: =IF(I50>0, MAX(0, I50-16)/2, "") -> 0 | L50: =J50*$B$1+K50*$B$2 -> 591.8 | M50: 7 | N50: Jennifer Wilson | P50: x | Q50: planned | R50: Service review call on 15th to discuss
A51: 7014638 | B51: HYTECK, SA d/b/a AROMA ZONE | C51: 6483387 | D51: Online | E51: VMware ESXi 7.0 | F51: Intel Xeon E5-2650 v4 2.2 GHz 12 Cores 24 Thrds 9.6 GT/s (w H/T) | G51: 28132867 | H51: 2661.6242 | I51: =IFERROR(__xludf.DUMMYFUNCTION("IFERROR(VALUE(REGEXEXTRACT(F51, ""(\d+)[-\s]?Cores?"")))"),12.0) -> 12 | J51: =IF(I51>0, 1, "") -> 1 | K51: =IF(I51>0, MAX(0, I51-16)/2, "") -> 0 | L51: =J51*$B$1+K51*$B$2 -> 591.8 | M51: 7 | N51: Jennifer Wilson | P51: x | Q51: planned | R51: Service review call on 15th to discuss
A52: 7014638 | B52: HYTECK, SA d/b/a AROMA ZONE | C52: 6483388 | D52: Online | E52: VMware ESXi 7.0 | F52: Intel Xeon E5-2650 v4 2.2 GHz 12 Cores 24 Thrds 9.6 GT/s (w H/T) | G52: 28132890 | H52: 2661.6242 | I52: =IFERROR(__xludf.DUMMYFUNCTION("IFERROR(VALUE(REGEXEXTRACT(F52, ""(\d+)[-\s]?Cores?"")))"),12.0) -> 12 | J52: =IF(I52>0, 1, "") -> 1 | K52: =IF(I52>0, MAX(0, I52-16)/2, "") -> 0 | L52: =J52*$B$1+K52*$B$2 -> 591.8 | M52: 7 | N52: Jennifer Wilson | P52: x | Q52: planned | R52: Service review call on 15th to discuss
A53: 7014638 | B53: HYTECK, SA d/b/a AROMA ZONE | C53: 6483388 | D53: Online | E53: VMware ESXi 7.0 | F53: Intel Xeon E5-2650 v4 2.2 GHz 12 Cores 24 Thrds 9.6 GT/s (w H/T) | G53: 28132891 | H53: 2661.6242 | I53: =IFERROR(__xludf.DUMMYFUNCTION("IFERROR(VALUE(REGEXEXTRACT(F53, ""(\d+)[-\s]?Cores?"")))"),12.0) -> 12 | J53: =IF(I53>0, 1, "") -> 1 | K53: =IF(I53>0, MAX(0, I53-16)/2, "") -> 0 | L53: =J53*$B$1+K53*$B$2 -> 591.8 | M53: 7 | N53: Jennifer Wilson | P53: x | Q53: planned | R53: Service review call on 15th to discuss
A54: 7014638 | B54: HYTECK, SA d/b/a AROMA ZONE | C54: 6483389 | D54: Online | E54: VMware ESXi 7.0 | F54: Intel Xeon E5-2650 v4 2.2 GHz 12 Cores 24 Thrds 9.6 GT/s (w H/T) | G54: 28132914 | H54: 2661.6242 | I54: =IFERROR(__xludf.DUMMYFUNCTION("IFERROR(VALUE(REGEXEXTRACT(F54, ""(\d+)[-\s]?Cores?"")))"),12.0) -> 12 | J54: =IF(I54>0, 1, "") -> 1 | K54: =IF(I54>0, MAX(0, I54-16)/2, "") -> 0 | L54: =J54*$B$1+K54*$B$2 -> 591.8 | M54: 7 | N54: Jennifer Wilson | P54: x | Q54: planned | R54: Service review call on 15th to discuss
A55: 7014638 | B55: HYTECK, SA d/b/a AROMA ZONE | C55: 6483389 | D55: Online | E55: VMware ESXi 7.0 | F55: Intel Xeon E5-2650 v4 2.2 GHz 12 Cores 24 Thrds 9.6 GT/s (w H/T) | G55: 28132915 | H55: 2661.6242 | I55: =IFERROR(__xludf.DUMMYFUNCTION("IFERROR(VALUE(REGEXEXTRACT(F55, ""(\d+)[-\s]?Cores?"")))"),12.0) -> 12 | J55: =IF(I55>0, 1, "") -> 1 | K55: =IF(I55>0, MAX(0, I55-16)/2, "") -> 0 | L55: =J55*$B$1+K55*$B$2 -> 591.8 | M55: 7 | N55: Jennifer Wilson | P55: x | Q55: planned | R55: Service review call on 15th to discuss
A56: 7006911 | B56: Blue Yonder Inc. | C56: 7297762 | D56: Online | E56: VMware ESXi 7.0 | F56: Intel Xeon E5-2650 v4 2.2 GHz 12 Cores 24 Thrds 9.6 GT/s (w H/T) | G56: 36133208 | H56: 4419.9241 | I56: =IFERROR(__xludf.DUMMYFUNCTION("IFERROR(VALUE(REGEXEXTRACT(F56, ""(\d+)[-\s]?Cores?"")))"),12.0) -> 12 | J56: =IF(I56>0, 1, "") -> 1 | K56: =IF(I56>0, MAX(0, I56-16)/2, "") -> 0 | L56: =J56*$B$1+K56*$B$2 -> 591.8 | M56: 7 | N56: Sean Small
A57: 7006911 | B57: Blue Yonder Inc. | C57: 7297762 | D57: Online | E57: VMware ESXi 7.0 | F57: Intel Xeon E5-2650 v4 2.2 GHz 12 Cores 24 Thrds 9.6 GT/s (w H/T) | G57: 36133209 | H57: 4419.9241 | I57: =IFERROR(__xludf.DUMMYFUNCTION("IFERROR(VALUE(REGEXEXTRACT(F57, ""(\d+)[-\s]?Cores?"")))"),12.0) -> 12 | J57: =IF(I57>0, 1, "") -> 1 | K57: =IF(I57>0, MAX(0, I57-16)/2, "") -> 0 | L57: =J57*$B$1+K57*$B$2 -> 591.8 | M57: 7 | N57: Sean Small
A58: 7006911 | B58: Blue Yonder Inc. | C58: 7297763 | D58: Online | E58: VMware ESXi 7.0 | F58: Intel Xeon E5-2650 v4 2.2 GHz 12 Cores 24 Thrds 9.6 GT/s (w H/T) | G58: 36133236 | H58: 4419.9241 | I58: =IFERROR(__xludf.DUMMYFUNCTION("IFERROR(VALUE(REGEXEXTRACT(F58, ""(\d+)[-\s]?Cores?"")))"),12.0) -> 12 | J58: =IF(I58>0, 1, "") -> 1 | K58: =IF(I58>0, MAX(0, I58-16)/2, "") -> 0 | L58: =J58*$B$1+K58*$B$2 -> 591.8 | M58: 7 | N58: Sean Small
A59: 7006911 | B59: Blue Yonder Inc. | C59: 7297763 | D59: Online | E59: VMware ESXi 7.0 | F59: Intel Xeon E5-2650 v4 2.2 GHz 12 Cores 24 Thrds 9.6 GT/s (w H/T) | G59: 36133237 | H59: 4419.9241 | I59: =IFERROR(__xludf.DUMMYFUNCTION("IFERROR(VALUE(REGEXEXTRACT(F59, ""(\d+)[-\s]?Cores?"")))"),12.0) -> 12 | J59: =IF(I59>0, 1, "") -> 1 | K59: =IF(I59>0, MAX(0, I59-16)/2, "") -> 0 | L59: =J59*$B$1+K59*$B$2 -> 591.8 | M59: 7 | N59: Sean Small
A60: 7006911 | B60: Blue Yonder Inc. | C60: 7297764 | D60: Online | E60: VMware ESXi 7.0 | F60: Intel Xeon E5-2650 v4 2.2 GHz 12 Cores 24 Thrds 9.6 GT/s (w H/T) | G60: 36133264 | H60: 4419.9241 | I60: =IFERROR(__xludf.DUMMYFUNCTION("IFERROR(VALUE(REGEXEXTRACT(F60, ""(\d+)[-\s]?Cores?"")))"),12.0) -> 12 | J60: =IF(I60>0, 1, "") -> 1 | K60: =IF(I60>0, MAX(0, I60-16)/2, "") -> 0 | L60: =J60*$B$1+K60*$B$2 -> 591.8 | M60: 7 | N60: Sean Small
A61: 7006911 | B61: Blue Yonder Inc. | C61: 7297764 | D61: Online | E61: VMware ESXi 7.0 | F61: Intel Xeon E5-2650 v4 2.2 GHz 12 Cores 24 Thrds 9.6 GT/s (w H/T) | G61: 36133265 | H61: 4419.9241 | I61: =IFERROR(__xludf.DUMMYFUNCTION("IFERROR(VALUE(REGEXEXTRACT(F61, ""(\d+)[-\s]?Cores?"")))"),12.0) -> 12 | J61: =IF(I61>0, 1, "") -> 1 | K61: =IF(I61>0, MAX(0, I61-16)/2, "") -> 0 | L61: =J61*$B$1+K61*$B$2 -> 591.8 | M61: 7 | N61: Sean Small
A62: 7006911 | B62: Blue Yonder Inc. | C62: 7297766 | D62: Online | E62: VMware ESXi 7.0 | F62: Intel Xeon E5-2650 v4 2.2 GHz 12 Cores 24 Thrds 9.6 GT/s (w H/T) | G62: 36133294 | H62: 4419.9241 | I62: =IFERROR(__xludf.DUMMYFUNCTION("IFERROR(VALUE(REGEXEXTRACT(F62, ""(\d+)[-\s]?Cores?"")))"),12.0) -> 12 | J62: =IF(I62>0, 1, "") -> 1 | K62: =IF(I62>0, MAX(0, I62-16)/2, "") -> 0 | L62: =J62*$B$1+K62*$B$2 -> 591.8 | M62: 7 | N62: Sean Small
A63: 7006911 | B63: Blue Yonder Inc. | C63: 7297766 | D63: Online | E63: VMware ESXi 7.0 | F63: Intel Xeon E5-2650 v4 2.2 GHz 12 Cores 24 Thrds 9.6 GT/s (w H/T) | G63: 36133295 | H63: 4419.9241 | I63: =IFERROR(__xludf.DUMMYFUNCTION("IFERROR(VALUE(REGEXEXTRACT(F63, ""(\d+)[-\s]?Cores?"")))"),12.0) -> 12 | J63: =IF(I63>0, 1, "") -> 1 | K63: =IF(I63>0, MAX(0, I63-16)/2, "") -> 0 | L63: =J63*$B$1+K63*$B$2 -> 591.8 | M63: 7 | N63: Sean Small
A64: 7014682 | B64: Combined Metal Industries Inc | C64: 7337256 | D64: Online | E64: VMware ESXi 7.0 | F64: Intel Xeon E5-2650 v4 2.2 GHz 12 Cores 24 Thrds 9.6 GT/s (w H/T) | G64: 36780901 | H64: 3123.32 | I64: =IFERROR(__xludf.DUMMYFUNCTION("IFERROR(VALUE(REGEXEXTRACT(F64, ""(\d+)[-\s]?Cores?"")))"),12.0) -> 12 | J64: =IF(I64>0, 1, "") -> 1 | K64: =IF(I64>0, MAX(0, I64-16)/2, "") -> 0 | L64: =J64*$B$1+K64*$B$2 -> 591.8 | M64: 7 | N64: Roland Gonzales | Q64: 10/8 DCO approved, Sent order to customer 10/6/25 Customer confirmed they can cancel vHost02 as part of migration to Azure | R64: Opportunity Created - waiting on Cody's recos
A65: 7014682 | B65: Combined Metal Industries Inc | C65: 7337256 | D65: Online | E65: VMware ESXi 7.0 | F65: Intel Xeon E5-2650 v4 2.2 GHz 12 Cores 24 Thrds 9.6 GT/s (w H/T) | G65: 36780902 | H65: 3123.32 | I65: =IFERROR(__xludf.DUMMYFUNCTION("IFERROR(VALUE(REGEXEXTRACT(F65, ""(\d+)[-\s]?Cores?"")))"),12.0) -> 12 | J65: =IF(I65>0, 1, "") -> 1 | K65: =IF(I65>0, MAX(0, I65-16)/2, "") -> 0 | L65: =J65*$B$1+K65*$B$2 -> 591.8 | M65: 7 | N65: Roland Gonzales | Q65: 10/8 DCO approved, Sent order to customer 10/6/25 Customer confirmed they can cancel vHost02 as part of migration to Azure | R65: Opportunity Created - waiting on Cody's recos
A66: 7014682 | B66: Combined Metal Industries Inc | C66: 7337257 | D66: Online | E66: VMware ESXi 7.0 | F66: Intel Xeon E5-2650 v4 2.2 GHz 12 Cores 24 Thrds 9.6 GT/s (w H/T) | G66: 36780926 | H66: 3123.32 | I66: =IFERROR(__xludf.DUMMYFUNCTION("IFERROR(VALUE(REGEXEXTRACT(F66, ""(\d+)[-\s]?Cores?"")))"),12.0) -> 12 | J66: =IF(I66>0, 1, "") -> 1 | K66: =IF(I66>0, MAX(0, I66-16)/2, "") -> 0 | L66: =J66*$B$1+K66*$B$2 -> 591.8 | M66: 7 | N66: Roland Gonzales | Q66: 10/8 DCO approved, Sent order to customer 10/6/25 Customer confirmed they can cancel vHost02 as part of migration to Azure | R66: Opportunity Created - waiting on Cody's recos
A67: 7014682 | B67: Combined Metal Industries Inc | C67: 7337257 | D67: Online | E67: VMware ESXi 7.0 | F67: Intel Xeon E5-2650 v4 2.2 GHz 12 Cores 24 Thrds 9.6 GT/s (w H/T) | G67: 36780927 | H67: 3123.32 | I67: =IFERROR(__xludf.DUMMYFUNCTION("IFERROR(VALUE(REGEXEXTRACT(F67, ""(\d+)[-\s]?Cores?"")))"),12.0) -> 12 | J67: =IF(I67>0, 1, "") -> 1 | K67: =IF(I67>0, MAX(0, I67-16)/2, "") -> 0 | L67: =J67*$B$1+K67*$B$2 -> 591.8 | M67: 7 | N67: Roland Gonzales | Q67: 10/8 DCO approved, Sent order to customer 10/6/25 Customer confirmed they can cancel vHost02 as part of migration to Azure | R67: Opportunity Created - waiting on Cody's recos
A68: 7014791 | B68: Chestnut Health System, Inc. | C68: 7848726 | D68: Online | E68: VMware ESXi 7.0 | F68: Intel Xeon E5-2670 v3 2.3 GHz 12 Cores 24 Threads 8 GT/s (w H/T) | G68: 43246101 | H68: 2120.3268 | I68: =IFERROR(__xludf.DUMMYFUNCTION("IFERROR(VALUE(REGEXEXTRACT(F68, ""(\d+)[-\s]?Cores?"")))"),12.0) -> 12 | J68: =IF(I68>0, 1, "") -> 1 | K68: =IF(I68>0, MAX(0, I68-16)/2, "") -> 0 | L68: =J68*$B$1+K68*$B$2 -> 591.8 | M68: 7 | N68: Roland Gonzales | O68: NO CHANGE at this time - will churn | Q68: No Action | R68: Opportunity Created - waiting on Cody's recos
A69: 7014791 | B69: Chestnut Health System, Inc. | C69: 7848726 | D69: Online | E69: VMware ESXi 7.0 | F69: Intel Xeon E5-2670 v3 2.3 GHz 12 Cores 24 Threads 8 GT/s (w H/T) | G69: 43246102 | H69: 2120.3268 | I69: =IFERROR(__xludf.DUMMYFUNCTION("IFERROR(VALUE(REGEXEXTRACT(F69, ""(\d+)[-\s]?Cores?"")))"),12.0) -> 12 | J69: =IF(I69>0, 1, "") -> 1 | K69: =IF(I69>0, MAX(0, I69-16)/2, "") -> 0 | L69: =J69*$B$1+K69*$B$2 -> 591.8 | M69: 7 | N69: Roland Gonzales | O69: NO CHANGE at this time - will churn | Q69: No Action | R69: Opportunity Created - waiting on Cody's recos
A70: 7014791 | B70: Chestnut Health System, Inc. | C70: 7848727 | D70: Online | E70: VMware ESXi 7.0 | F70: Intel Xeon E5-2670 v3 2.3 GHz 12 Cores 24 Threads 8 GT/s (w H/T) | G70: 43246122 | H70: 2120.3268 | I70: =IFERROR(__xludf.DUMMYFUNCTION("IFERROR(VALUE(REGEXEXTRACT(F70, ""(\d+)[-\s]?Cores?"")))"),12.0) -> 12 | J70: =IF(I70>0, 1, "") -> 1 | K70: =IF(I70>0, MAX(0, I70-16)/2, "") -> 0 | L70: =J70*$B$1+K70*$B$2 -> 591.8 | M70: 7 | N70: Roland Gonzales | O70: NO CHANGE at this time - will churn | Q70: No Action | R70: Opportunity Created - waiting on Cody's recos
A71: 7014791 | B71: Chestnut Health System, Inc. | C71: 7848727 | D71: Online | E71: VMware ESXi 7.0 | F71: Intel Xeon E5-2670 v3 2.3 GHz 12 Cores 24 Threads 8 GT/s (w H/T) | G71: 43246123 | H71: 2120.3268 | I71: =IFERROR(__xludf.DUMMYFUNCTION("IFERROR(VALUE(REGEXEXTRACT(F71, ""(\d+)[-\s]?Cores?"")))"),12.0) -> 12 | J71: =IF(I71>0, 1, "") -> 1 | K71: =IF(I71>0, MAX(0, I71-16)/2, "") -> 0 | L71: =J71*$B$1+K71*$B$2 -> 591.8 | M71: 7 | N71: Roland Gonzales | O71: NO CHANGE at this time - will churn | Q71: No Action | R71: Opportunity Created - waiting on Cody's recos
A72: 7036572 | B72: Alaya Care Inc | C72: 5643824 | D72: Online | E72: VMware ESXi 6.5 | F72: Default Intel Xeon Gold 5118 2.3 GHz 12 Cores 24/T (105W TDP) | G72: 21319000 | H72: 2174.56 | I72: =IFERROR(__xludf.DUMMYFUNCTION("IFERROR(VALUE(REGEXEXTRACT(F72, ""(\d+)[-\s]?Cores?"")))"),12.0) -> 12 | J72: =IF(I72>0, 1, "") -> 1 | K72: =IF(I72>0, MAX(0, I72-16)/2, "") -> 0 | L72: =J72*$B$1+K72*$B$2 -> 591.8 | M72: 7,8 | N72: Marko Andjelkovic | R72: Waiting on information from the customer
A73: 7036572 | B73: Alaya Care Inc | C73: 5643824 | D73: Online | E73: VMware ESXi 6.5 | F73: Default Intel Xeon Gold 5118 2.3 GHz 12 Cores 24/T (105W TDP) | G73: 21319001 | H73: 2174.56 | I73: =IFERROR(__xludf.DUMMYFUNCTION("IFERROR(VALUE(REGEXEXTRACT(F73, ""(\d+)[-\s]?Cores?"")))"),12.0) -> 12 | J73: =IF(I73>0, 1, "") -> 1 | K73: =IF(I73>0, MAX(0, I73-16)/2, "") -> 0 | L73: =J73*$B$1+K73*$B$2 -> 591.8 | M73: 7,8 | N73: Marko Andjelkovic | R73: Waiting on information from the customer
A74: 7036572 | B74: Alaya Care Inc | C74: 5643830 | D74: Online | E74: VMware ESXi 6.5 | F74: Default Intel Xeon Gold 5118 2.3 GHz 12 Cores 24/T (105W TDP) | G74: 21319124 | H74: 2174.56 | I74: =IFERROR(__xludf.DUMMYFUNCTION("IFERROR(VALUE(REGEXEXTRACT(F74, ""(\d+)[-\s]?Cores?"")))"),12.0) -> 12 | J74: =IF(I74>0, 1, "") -> 1 | K74: =IF(I74>0, MAX(0, I74-16)/2, "") -> 0 | L74: =J74*$B$1+K74*$B$2 -> 591.8 | M74: 7,8 | N74: Marko Andjelkovic | R74: Waiting on information from the customer
A75: 7036572 | B75: Alaya Care Inc | C75: 5643830 | D75: Online | E75: VMware ESXi 6.5 | F75: Default Intel Xeon Gold 5118 2.3 GHz 12 Cores 24/T (105W TDP) | G75: 21319125 | H75: 2174.56 | I75: =IFERROR(__xludf.DUMMYFUNCTION("IFERROR(VALUE(REGEXEXTRACT(F75, ""(\d+)[-\s]?Cores?"")))"),12.0) -> 12 | J75: =IF(I75>0, 1, "") -> 1 | K75: =IF(I75>0, MAX(0, I75-16)/2, "") -> 0 | L75: =J75*$B$1+K75*$B$2 -> 591.8 | M75: 7,8 | N75: Marko Andjelkovic | R75: Waiting on information from the customer
A76: 7000167 | B76: Enidus USA, LLC | C76: 6096495 | D76: Online | E76: VMware ESXi 7.0 | F76: Intel Xeon Gold 5118 2.3 GHz 12 Cores 24/T (105W TDP) | G76: 25470269 | H76: 3082.3742 | I76: =IFERROR(__xludf.DUMMYFUNCTION("IFERROR(VALUE(REGEXEXTRACT(F76, ""(\d+)[-\s]?Cores?"")))"),12.0) -> 12 | J76: =IF(I76>0, 1, "") -> 1 | K76: =IF(I76>0, MAX(0, I76-16)/2, "") -> 0 | L76: =J76*$B$1+K76*$B$2 -> 591.8 | M76: 7,8 | N76: Roger Gonzales
A77: 7000167 | B77: Enidus USA, LLC | C77: 6096495 | D77: Online | E77: VMware ESXi 7.0 | F77: Intel Xeon Gold 5118 2.3 GHz 12 Cores 24/T (105W TDP) | G77: 25470270 | H77: 3082.3742 | I77: =IFERROR(__xludf.DUMMYFUNCTION("IFERROR(VALUE(REGEXEXTRACT(F77, ""(\d+)[-\s]?Cores?"")))"),12.0) -> 12 | J77: =IF(I77>0, 1, "") -> 1 | K77: =IF(I77>0, MAX(0, I77-16)/2, "") -> 0 | L77: =J77*$B$1+K77*$B$2 -> 591.8 | M77: 7,8 | N77: Roger Gonzales
A78: 7014917 | B78: Leek United Building Society | C78: 6411959 | D78: Migration | E78: VMware ESXi 7.0 | F78: Default Intel Xeon Gold 5118 2.3 GHz 12 Cores/ 24T (105W TDP) | G78: 27534257 | H78: 2754.9118 | I78: =IFERROR(__xludf.DUMMYFUNCTION("IFERROR(VALUE(REGEXEXTRACT(F78, ""(\d+)[-\s]?Cores?"")))"),12.0) -> 12 | J78: =IF(I78>0, 1, "") -> 1 | K78: =IF(I78>0, MAX(0, I78-16)/2, "") -> 0 | L78: =J78*$B$1+K78*$B$2 -> 591.8 | M78: 7,8 | N78: Darren Wells | O78: New 3Y Contract | P78: Weekly | R78: Server Refresh Migration Project
A79: 7014917 | B79: Leek United Building Society | C79: 6411959 | D79: Migration | E79: VMware ESXi 7.0 | F79: Default Intel Xeon Gold 5118 2.3 GHz 12 Cores/ 24T (105W TDP) | G79: 27534258 | H79: 2754.9118 | I79: =IFERROR(__xludf.DUMMYFUNCTION("IFERROR(VALUE(REGEXEXTRACT(F79, ""(\d+)[-\s]?Cores?"")))"),12.0) -> 12 | J79: =IF(I79>0, 1, "") -> 1 | K79: =IF(I79>0, MAX(0, I79-16)/2, "") -> 0 | L79: =J79*$B$1+K79*$B$2 -> 591.8 | M79: 7,8 | N79: Darren Wells | O79: New 3Y Contract | P79: Weekly | R79: Server Refresh Migration Project
A80: 7014917 | B80: Leek United Building Society | C80: 6411960 | D80: Migration | E80: VMware ESXi 7.0 | F80: Default Intel Xeon Gold 5118 2.3 GHz 12 Cores/ 24T (105W TDP) | G80: 27534287 | H80: 2754.9118 | I80: =IFERROR(__xludf.DUMMYFUNCTION("IFERROR(VALUE(REGEXEXTRACT(F80, ""(\d+)[-\s]?Cores?"")))"),12.0) -> 12 | J80: =IF(I80>0, 1, "") -> 1 | K80: =IF(I80>0, MAX(0, I80-16)/2, "") -> 0 | L80: =J80*$B$1+K80*$B$2 -> 591.8 | M80: 7,8 | N80: Darren Wells | O80: New 3Y Contract | P80: Weekly | R80: Server Refresh Migration Project
A81: 7014917 | B81: Leek United Building Society | C81: 6411960 | D81: Migration | E81: VMware ESXi 7.0 | F81: Default Intel Xeon Gold 5118 2.3 GHz 12 Cores/ 24T (105W TDP) | G81: 27534288 | H81: 2754.9118 | I81: =IFERROR(__xludf.DUMMYFUNCTION("IFERROR(VALUE(REGEXEXTRACT(F81, ""(\d+)[-\s]?Cores?"")))"),12.0) -> 12 | J81: =IF(I81>0, 1, "") -> 1 | K81: =IF(I81>0, MAX(0, I81-16)/2, "") -> 0 | L81: =J81*$B$1+K81*$B$2 -> 591.8 | M81: 7,8 | N81: Darren Wells | O81: New 3Y Contract | P81: Weekly | R81: Server Refresh Migration Project
A82: 7014917 | B82: Leek United Building Society | C82: 6411961 | D82: Migration | E82: VMware ESXi 7.0 | F82: Default Intel Xeon Gold 5118 2.3 GHz 12 Cores/ 24T (105W TDP) | G82: 27534317 | H82: 2754.9118 | I82: =IFERROR(__xludf.DUMMYFUNCTION("IFERROR(VALUE(REGEXEXTRACT(F82, ""(\d+)[-\s]?Cores?"")))"),12.0) -> 12 | J82: =IF(I82>0, 1, "") -> 1 | K82: =IF(I82>0, MAX(0, I82-16)/2, "") -> 0 | L82: =J82*$B$1+K82*$B$2 -> 591.8 | M82: 7,8 | N82: Darren Wells | O82: New 3Y Contract | P82: Weekly | R82: Server Refresh Migration Project
A83: 7014917 | B83: Leek United Building Society | C83: 6411961 | D83: Migration | E83: VMware ESXi 7.0 | F83: Default Intel Xeon Gold 5118 2.3 GHz 12 Cores/ 24T (105W TDP) | G83: 27534318 | H83: 2754.9118 | I83: =IFERROR(__xludf.DUMMYFUNCTION("IFERROR(VALUE(REGEXEXTRACT(F83, ""(\d+)[-\s]?Cores?"")))"),12.0) -> 12 | J83: =IF(I83>0, 1, "") -> 1 | K83: =IF(I83>0, MAX(0, I83-16)/2, "") -> 0 | L83: =J83*$B$1+K83*$B$2 -> 591.8 | M83: 7,8 | N83: Darren Wells | O83: New 3Y Contract | P83: Weekly | R83: Server Refresh Migration Project
A84: 7014917 | B84: Leek United Building Society | C84: 6411962 | D84: Migration | E84: VMware ESXi 7.0 | F84: Default Intel Xeon Gold 5118 2.3 GHz 12 Cores/ 24T (105W TDP) | G84: 27534347 | H84: 2754.9118 | I84: =IFERROR(__xludf.DUMMYFUNCTION("IFERROR(VALUE(REGEXEXTRACT(F84, ""(\d+)[-\s]?Cores?"")))"),12.0) -> 12 | J84: =IF(I84>0, 1, "") -> 1 | K84: =IF(I84>0, MAX(0, I84-16)/2, "") -> 0 | L84: =J84*$B$1+K84*$B$2 -> 591.8 | M84: 7,8 | N84: Darren Wells | O84: New 3Y Contract | P84: Weekly | R84: Server Refresh Migration Project
A85: 7014917 | B85: Leek United Building Society | C85: 6411962 | D85: Migration | E85: VMware ESXi 7.0 | F85: Default Intel Xeon Gold 5118 2.3 GHz 12 Cores/ 24T (105W TDP) | G85: 27534348 | H85: 2754.9118 | I85: =IFERROR(__xludf.DUMMYFUNCTION("IFERROR(VALUE(REGEXEXTRACT(F85, ""(\d+)[-\s]?Cores?"")))"),12.0) -> 12 | J85: =IF(I85>0, 1, "") -> 1 | K85: =IF(I85>0, MAX(0, I85-16)/2, "") -> 0 | L85: =J85*$B$1+K85*$B$2 -> 591.8 | M85: 7,8 | N85: Darren Wells | O85: New 3Y Contract | P85: Weekly | R85: Server Refresh Migration Project
A86: 5401567 | B86: Kinetico | C86: 6464705 | D86: Online | E86: VMware ESXi 7.0 | F86: Default Intel Xeon Gold 5118 2.3 GHz 12 Cores/ 24T (105W TDP) | G86: 27831289 | H86: 2320.5082 | I86: =IFERROR(__xludf.DUMMYFUNCTION("IFERROR(VALUE(REGEXEXTRACT(F86, ""(\d+)[-\s]?Cores?"")))"),12.0) -> 12 | J86: =IF(I86>0, 1, "") -> 1 | K86: =IF(I86>0, MAX(0, I86-16)/2, "") -> 0 | L86: =J86*$B$1+K86*$B$2 -> 591.8 | M86: 7,8 | N86: Roger Gonzales
A87: 5401567 | B87: Kinetico | C87: 6464705 | D87: Online | E87: VMware ESXi 7.0 | F87: Default Intel Xeon Gold 5118 2.3 GHz 12 Cores/ 24T (105W TDP) | G87: 27831290 | H87: 2320.5082 | I87: =IFERROR(__xludf.DUMMYFUNCTION("IFERROR(VALUE(REGEXEXTRACT(F87, ""(\d+)[-\s]?Cores?"")))"),12.0) -> 12 | J87: =IF(I87>0, 1, "") -> 1 | K87: =IF(I87>0, MAX(0, I87-16)/2, "") -> 0 | L87: =J87*$B$1+K87*$B$2 -> 591.8 | M87: 7,8 | N87: Roger Gonzales
A88: 5401567 | B88: Kinetico | C88: 6464706 | D88: Online | E88: VMware ESXi 7.0 | F88: Default Intel Xeon Gold 5118 2.3 GHz 12 Cores/ 24T (105W TDP) | G88: 27831316 | H88: 2320.5082 | I88: =IFERROR(__xludf.DUMMYFUNCTION("IFERROR(VALUE(REGEXEXTRACT(F88, ""(\d+)[-\s]?Cores?"")))"),12.0) -> 12 | J88: =IF(I88>0, 1, "") -> 1 | K88: =IF(I88>0, MAX(0, I88-16)/2, "") -> 0 | L88: =J88*$B$1+K88*$B$2 -> 591.8 | M88: 7,8 | N88: Roger Gonzales
A89: 5401567 | B89: Kinetico | C89: 6464706 | D89: Online | E89: VMware ESXi 7.0 | F89: Default Intel Xeon Gold 5118 2.3 GHz 12 Cores/ 24T (105W TDP) | G89: 27831317 | H89: 2320.5082 | I89: =IFERROR(__xludf.DUMMYFUNCTION("IFERROR(VALUE(REGEXEXTRACT(F89, ""(\d+)[-\s]?Cores?"")))"),12.0) -> 12 | J89: =IF(I89>0, 1, "") -> 1 | K89: =IF(I89>0, MAX(0, I89-16)/2, "") -> 0 | L89: =J89*$B$1+K89*$B$2 -> 591.8 | M89: 7,8 | N89: Roger Gonzales
A90: 7000167 | B90: Enidus USA, LLC | C90: 6465016 | D90: Online | E90: VMware ESXi 7.0 | F90: Default Intel Xeon Gold 5118 2.3 GHz 12 Cores/ 24T (105W TDP) | G90: 27833280 | H90: 2568.0027 | I90: =IFERROR(__xludf.DUMMYFUNCTION("IFERROR(VALUE(REGEXEXTRACT(F90, ""(\d+)[-\s]?Cores?"")))"),12.0) -> 12 | J90: =IF(I90>0, 1, "") -> 1 | K90: =IF(I90>0, MAX(0, I90-16)/2, "") -> 0 | L90: =J90*$B$1+K90*$B$2 -> 591.8 | M90: 7,8 | N90: Roger Gonzales
A91: 7000167 | B91: Enidus USA, LLC | C91: 6465016 | D91: Online | E91: VMware ESXi 7.0 | F91: Default Intel Xeon Gold 5118 2.3 GHz 12 Cores/ 24T (105W TDP) | G91: 27833281 | H91: 2568.0027 | I91: =IFERROR(__xludf.DUMMYFUNCTION("IFERROR(VALUE(REGEXEXTRACT(F91, ""(\d+)[-\s]?Cores?"")))"),12.0) -> 12 | J91: =IF(I91>0, 1, "") -> 1 | K91: =IF(I91>0, MAX(0, I91-16)/2, "") -> 0 | L91: =J91*$B$1+K91*$B$2 -> 591.8 | M91: 7,8 | N91: Roger Gonzales
A92: 7000167 | B92: Enidus USA, LLC | C92: 6465017 | D92: Online | E92: VMware ESXi 7.0 | F92: Default Intel Xeon Gold 5118 2.3 GHz 12 Cores/ 24T (105W TDP) | G92: 27833320 | H92: 2499.7381 | I92: =IFERROR(__xludf.DUMMYFUNCTION("IFERROR(VALUE(REGEXEXTRACT(F92, ""(\d+)[-\s]?Cores?"")))"),12.0) -> 12 | J92: =IF(I92>0, 1, "") -> 1 | K92: =IF(I92>0, MAX(0, I92-16)/2, "") -> 0 | L92: =J92*$B$1+K92*$B$2 -> 591.8 | M92: 7,8 | N92: Roger Gonzales
A93: 7000167 | B93: Enidus USA, LLC | C93: 6465017 | D93: Online | E93: VMware ESXi 7.0 | F93: Default Intel Xeon Gold 5118 2.3 GHz 12 Cores/ 24T (105W TDP) | G93: 27833321 | H93: 2499.7381 | I93: =IFERROR(__xludf.DUMMYFUNCTION("IFERROR(VALUE(REGEXEXTRACT(F93, ""(\d+)[-\s]?Cores?"")))"),12.0) -> 12 | J93: =IF(I93>0, 1, "") -> 1 | K93: =IF(I93>0, MAX(0, I93-16)/2, "") -> 0 | L93: =J93*$B$1+K93*$B$2 -> 591.8 | M93: 7,8 | N93: Roger Gonzales
A94: 5401567 | B94: Kinetico | C94: 7023229 | D94: Online | E94: VMware ESXi 7.0 | F94: Default Intel Xeon Gold 5118 2.3 GHz 12 Cores/ 24T (105W TDP) | G94: 33422705 | H94: 3010.5524 | I94: =IFERROR(__xludf.DUMMYFUNCTION("IFERROR(VALUE(REGEXEXTRACT(F94, ""(\d+)[-\s]?Cores?"")))"),12.0) -> 12 | J94: =IF(I94>0, 1, "") -> 1 | K94: =IF(I94>0, MAX(0, I94-16)/2, "") -> 0 | L94: =J94*$B$1+K94*$B$2 -> 591.8 | M94: 7,8 | N94: Roger Gonzales
A95: 5401567 | B95: Kinetico | C95: 7023229 | D95: Online | E95: VMware ESXi 7.0 | F95: Default Intel Xeon Gold 5118 2.3 GHz 12 Cores/ 24T (105W TDP) | G95: 33422706 | H95: 3010.5524 | I95: =IFERROR(__xludf.DUMMYFUNCTION("IFERROR(VALUE(REGEXEXTRACT(F95, ""(\d+)[-\s]?Cores?"")))"),12.0) -> 12 | J95: =IF(I95>0, 1, "") -> 1 | K95: =IF(I95>0, MAX(0, I95-16)/2, "") -> 0 | L95: =J95*$B$1+K95*$B$2 -> 591.8 | M95: 7,8 | N95: Roger Gonzales
A96: 5401567 | B96: Kinetico | C96: 7023230 | D96: Online | E96: VMware ESXi 7.0 | F96: Default Intel Xeon Gold 5118 2.3 GHz 12 Cores/ 24T (105W TDP) | G96: 33422736 | H96: 3010.5524 | I96: =IFERROR(__xludf.DUMMYFUNCTION("IFERROR(VALUE(REGEXEXTRACT(F96, ""(\d+)[-\s]?Cores?"")))"),12.0) -> 12 | J96: =IF(I96>0, 1, "") -> 1 | K96: =IF(I96>0, MAX(0, I96-16)/2, "") -> 0 | L96: =J96*$B$1+K96*$B$2 -> 591.8 | M96: 7,8 | N96: Roger Gonzales
A97: 5401567 | B97: Kinetico | C97: 7023230 | D97: Online | E97: VMware ESXi 7.0 | F97: Default Intel Xeon Gold 5118 2.3 GHz 12 Cores/ 24T (105W TDP) | G97: 33422737 | H97: 3010.5524 | I97: =IFERROR(__xludf.DUMMYFUNCTION("IFERROR(VALUE(REGEXEXTRACT(F97, ""(\d+)[-\s]?Cores?"")))"),12.0) -> 12 | J97: =IF(I97>0, 1, "") -> 1 | K97: =IF(I97>0, MAX(0, I97-16)/2, "") -> 0 | L97: =J97*$B$1+K97*$B$2 -> 591.8 | M97: 7,8 | N97: Roger Gonzales
A98: 7011090 | B98: Netintegrity Inc | C98: 7244266 | D98: Online | E98: VMware ESXi 7.0 | F98: Default Intel Xeon Gold 5118 2.3 GHz 12 Cores/ 24T (105W TDP) | G98: 34967312 | H98: 1604.3 | I98: =IFERROR(__xludf.DUMMYFUNCTION("IFERROR(VALUE(REGEXEXTRACT(F98, ""(\d+)[-\s]?Cores?"")))"),12.0) -> 12 | J98: =IF(I98>0, 1, "") -> 1 | K98: =IF(I98>0, MAX(0, I98-16)/2, "") -> 0 | L98: =J98*$B$1+K98*$B$2 -> 591.8 | M98: 7,8 | N98: Roland Gonzales | Q98: 10/10 customer approved 278891 - DCO to install - 10/6/25 Waiting customer to approve in place upgrade - order 278891 | R98: Opportunity Created - waiting on Cody's recos
A99: 7011090 | B99: Netintegrity Inc | C99: 7244266 | D99: Online | E99: VMware ESXi 7.0 | F99: Default Intel Xeon Gold 5118 2.3 GHz 12 Cores/ 24T (105W TDP) | G99: 34967313 | H99: 1604.3 | I99: =IFERROR(__xludf.DUMMYFUNCTION("IFERROR(VALUE(REGEXEXTRACT(F99, ""(\d+)[-\s]?Cores?"")))"),12.0) -> 12 | J99: =IF(I99>0, 1, "") -> 1 | K99: =IF(I99>0, MAX(0, I99-16)/2, "") -> 0 | L99: =J99*$B$1+K99*$B$2 -> 591.8 | M99: 7,8 | N99: Roland Gonzales | Q99: 10/10 customer approved 278891 - DCO to install - 10/6/25 Waiting customer to approve in place upgrade - order 278891 | R99: Opportunity Created - waiting on Cody's recos
A100: 7011090 | B100: Netintegrity Inc | C100: 7244268 | D100: Online | E100: VMware ESXi 7.0 | F100: Default Intel Xeon Gold 5118 2.3 GHz 12 Cores/ 24T (105W TDP) | G100: 34967344 | H100: 1604.3 | I100: =IFERROR(__xludf.DUMMYFUNCTION("IFERROR(VALUE(REGEXEXTRACT(F100, ""(\d+)[-\s]?Cores?"")))"),12.0) -> 12 | J100: =IF(I100>0, 1, "") -> 1 | K100: =IF(I100>0, MAX(0, I100-16)/2, "") -> 0 | L100: =J100*$B$1+K100*$B$2 -> 591.8 | M100: 7,8 | N100: Roland Gonzales | Q100: 10/10 customer approved 278891 - DCO to install - 10/6/25 Waiting customer to approve in place upgrade - order 278891 | R100: Opportunity Created - waiting on Cody's recos
A101: 7011090 | B101: Netintegrity Inc | C101: 7244268 | D101: Online | E101: VMware ESXi 7.0 | F101: Default Intel Xeon Gold 5118 2.3 GHz 12 Cores/ 24T (105W TDP) | G101: 34967345 | H101: 1604.3 | I101: =IFERROR(__xludf.DUMMYFUNCTION("IFERROR(VALUE(REGEXEXTRACT(F101, ""(\d+)[-\s]?Cores?"")))"),12.0) -> 12 | J101: =IF(I101>0, 1, "") -> 1 | K101: =IF(I101>0, MAX(0, I101-16)/2, "") -> 0 | L101: =J101*$B$1+K101*$B$2 -> 591.8 | M101: 7,8 | N101: Roland Gonzales | Q101: 10/10 customer approved 278891 - DCO to install - 10/6/25 Waiting customer to approve in place upgrade - order 278891 | R101: Opportunity Created - waiting on Cody's recos
...

Sheet Tracking
A1: Customer | B1: SF Opportunity | C1: GSE # | D1: CQP Link | E1: Status/Notes | F1: Ticket ID(s)
A2: Cenovus Energy Inc. | B2: https://aptum.lightning.force.com/lightning/r/006OF00000R18iLYAR/view | C2: 190 | D2: Cenovus Energy Inc.xlsm | E2: Discussions with customer on how they want to proceed. Currently only have 1 Guest on their solution that they are using. 3 options with customer currently
A3: ViOptix, Inc. - PO # 1357 | B3: https://aptum.lightning.force.com/lightning/r/006OF00000R5QTsYAN/view | C3: 194 | E3: New Servers Ordered for New Gear and ESXi 8
A4: BCOM 2000 HOLDINGS PTY LTD | E4: CPQ sent to AM
A5: HYTECK, SA d/b/a AROMA ZONE | E5: CPQ sent to AM. Options have been sent to the customer and Mike is working with them currently on which option to move forward with.
A6: Enidus USA, LLC | B6: https://aptum.lightning.force.com/lightning/r/006OF00000QUMCEYA5/view | C6: 200 | E6: Hector | F6: https://aptum.atlassian.net/browse/APTUM-52322
A7: Netintegrity Inc | B7: https://aptum.lightning.force.com/lightning/r/006OF00000QSb0rYAD/view | C7: 202 | E7: Charles Rutledge | F7: https://aptum.atlassian.net/jira/servicedesk/projects/APTUM/queues/custom/852/APTUM-32273
A8: Heilind Electronics, Inc. | B8: https://aptum.lightning.force.com/lightning/r/Opportunity/006OF00000MRrzhYAD/view | E8: Customer is migrating to 650xs-Hector | F8: https://aptum.atlassian.net/browse/APTUM-51667
A9: Nikon Instruments Inc. | B9: https://aptum.lightning.force.com/lightning/r/006OF00000R0yBAYAZ/view | C9: 209 | E9: Waiting to hear back from the customer.
A10: eMetrix Systems, LLC | B10: https://aptum.lightning.force.com/lightning/r/006OF00000QjQx5YAF/view | C10: 210 | E10: Steve has this in his list of things to do and will reach out to the customer again.
A11: Currencies Direct Ltd | B11: https://aptum.lightning.force.com/lightning/r/006OF00000QTvAQYA1/view | C11: 191 | E11: scheduling to upgrade to 8: Oct 5th; updated to V8 Completed | F11: https://aptum.atlassian.net/browse/APTUM-29283
A12: 20-20 Technologies inc. | E12: Churning end of October. Customer is not using the servers.
A13: Internet Edge Solutions Inc. | B13: https://aptum.lightning.force.com/lightning/r/006OF00000QSOJoYAP/view | C13: 192 | D13: Internet Edge Solutions 1.xlsm | E13: CPQ sent to AM-Gary Cox completed-Jan 18th | F13: https://aptum.atlassian.net/browse/APTUM-38960
A14: ENTREGAS PUNTUALES S DE RL DE CV | B14: https://aptum.lightning.force.com/lightning/r/Opportunity/006OF00000PKdJlYAL/view | E14: Currently migrating to latest version-Completed
A15: Premia Solutions Limited | E15: Churning during next 2 months
A16: Interpro Technology Solutions Limited | E16: Churning end of October
A17: Nomad Digital Inc. | B17: https://aptum.lightning.force.com/lightning/r/006OF00000QToNTYA1/view | C17: 193 | D17: Nomad Digital 1.xlsm | E17: Completed- Sam Messer-11/26 | F17: https://aptum.atlassian.net/browse/APTUM-35440
A18: Chestnut Health System, Inc. | B18: https://aptum.lightning.force.com/lightning/r/006OF00000QSGsYYAX/view https://aptum.lightning.force.com/lightning/r/006OF00000QSXRvYAP/view | C18: 195 | E18: Churning Toronto end of October. They're waiting to complete their existing term. Atlanta will stay online. Miami will stay online until the end of July. Toronto will continue to July, but keep two hosts in Toronto.
A19: Global Maritime Transportation Services, Inc. | B19: https://aptum.lightning.force.com/lightning/r/006OF00000QUL4sYAH/view | C19: 196 | E19: Justin- Completed Dec 11th. | F19: https://aptum.atlassian.net/browse/APTUM-36306
A20: Currency Stream International Limited | B20: https://aptum.lightning.force.com/lightning/r/006OF00000QTspGYAT/view | C20: 197 | E20: Reached out to Jennifer regarding this one.
A21: Blue Yonder Inc. | B21: https://aptum.lightning.force.com/lightning/r/Opportunity/006OF00000OZoHpYAL/view | C21: 151 | E21: Is this order from June taking care of the situation at this customer?
A22: Combined Metal Industries Inc | B22: https://aptum.lightning.force.com/lightning/r/006OF00000QSQOrYAP/view | C22: 198 | D22: Combined Metal 1.xlsm | E22: Churning during next 2 months. They're currently migrating to Azure
A23: Alaya Care Inc | B23: https://aptum.lightning.force.com/lightning/r/006OF00000R152xYAB/view | C23: 199 | E23: Scheduling to upgrade to 8: Oct 5th; updated to V8 completed | F23: APTUM-29282
A24: Leek United Building Society | B24: https://aptum.lightning.force.com/lightning/r/Opportunity/006OF00000HTOQBYA5/view | E24: Covered under that opportunity- Completed-Will
A25: Kinetico | B25: https://aptum.lightning.force.com/lightning/r/006OF00000QUGpyYAH/view | C25: 201 | D25: Kinetico - ATL.xlsm https://disks.sharepoint.com/:x:/r/sites/GSESalesEngagement/Shared%20Documents/GSE%20Requests/%5BGSE-201%5D%20Kinetico%20Incorporated%20(d/Kinetico%20-%20POR.xlsm?d=w4d75ac7fa12e48aab00f395d9b9b5a7a&csf=1&web=1&e=DqHcuU | E25: Gary Cox-POR done, Atl completed | F25: https://aptum.atlassian.net/browse/APTUM-37165
A26: Adam Matthew Digital | B26: https://aptum.lightning.force.com/lightning/r/006OF00000QirEYYAZ/view | C26: 203 | E26: Justin-waiting on vcenter provision-Completed-02-01 | F26: APTUM-38068
A27: Star One Credit Union | B27: https://aptum.lightning.force.com/lightning/r/006OF00000QjVyPYAV/view | C27: 204 | E27: Churning end of October
A28: Better Impact Inc. | B28: https://aptum.lightning.force.com/lightning/r/006OF00000QU6QsYAL/view | C28: 205 | E28: This will be an Inplace Upgrade-Gary Cox-Completed-01-23 | F28: https://aptum.atlassian.net/browse/APTUM-40519
A29: Townsquare Media | B29: https://aptum.lightning.force.com/lightning/r/Opportunity/006OF00000QUHAvYAP/view | E29: OrderID 278843, 278844-Chris Templeman, Scheduled Nov 30th-Completed | F29: APTUM-28930
A30: RepoSystems.Com Inc. | B30: https://aptum.lightning.force.com/lightning/r/006OF00000QUMQlYAP/view | C30: 206 | E30: CPQ sent to AM-Gary Cox-Completed-Jan 11th | F30: https://aptum.atlassian.net/browse/APTUM-39965
A31: Transformify Ltd | B31: https://aptum.lightning.force.com/lightning/r/006OF00000QTt8dYAD/view | C31: 207 | E31: Will Mariner-Completed=Oct 24th | F31: https://aptum.atlassian.net/jira/servicedesk/projects/APTUM/queues/custom/852/APTUM-32486
A32: dbridge inc. | B32: https://aptum.lightning.force.com/lightning/r/006OF00000QULzJYAX/view | C32: 208 | E32: CPQ sent to AM-Gary Cox-Completed-Jan 11th | F32: https://aptum.atlassian.net/browse/APTUM-39946
A33: Fermi Investments | B33: https://aptum.lightning.force.com/lightning/r/006OF00000QTechYAD/view | C33: 211 | E33: Reached out to Jennifer regarding this one.
A34: CITYWAY | B34: https://aptum.lightning.force.com/lightning/r/Opportunity/006OF00000PZWkzYAH/view | C34: 164 | E34: CPQ sent to AM
A35: Vanquis | B35: https://aptum.lightning.force.com/lightning/r/Opportunity/006OF00000PFwN4YAL/view | E35: In process-Chris Templeman-Done
A36: Supplier Solutions | B36: https://aptum.lightning.force.com/lightning/r/Opportunity/006OF00000PmB62YAF/view | E36: Already on 8. Working on a refresh (larger solution)
A37: Granite REIT Holdings Limited Partnership | B37: https://aptum.lightning.force.com/lightning/r/006OF00000QSbGzYAL/view | C37: 212 | E37: Gary Cox-completed 10-31-2025 | F37: https://aptum.atlassian.net/jira/servicedesk/projects/APTUM/queues/custom/852/APTUM-32364
A38: Engage People Inc. | B38: https://aptum.lightning.force.com/lightning/r/006OF00000QSZS8YAP/view | C38: 213 | E38: Hector Iriarte-Complete-upgraded to 8.
A39: Ministry of Education Jamaica | B39: https://aptum.lightning.force.com/lightning/r/006OF00000QUBLiYAP/view | C39: 214 | E39: In place upgrade-Completed-Gary Cox | F39: https://aptum.atlassian.net/browse/APTUM-40169
A40: Collins Trucking Company, Inc | B40: https://aptum.lightning.force.com/lightning/r/006OF00000QjfcjYAB/view | C40: 215 | E40: CPQ sent to AM - Have not heard back from the customer as of yet.
A41: Arctrieval, Inc | E41: This has been upgraded already.
A42: WeirFoulds LLP | B42: https://aptum.lightning.force.com/lightning/r/006OF00000QST06YAH/view | C42: 216 | E42: Leaving due to Price increases and cost.
A43: Chicken Farmers Of Ontario | B43: https://aptum.lightning.force.com/lightning/r/006OF00000QSVRjYAP/view | C43: 217 | E43: Hector/Justin- Completed 01-25 | F43: https://aptum.atlassian.net/browse/APTUM-36302

Sheet Original Spreadsheet
A1: Client ID | B1: Company Name | C1: Account Manager | D1: TAM | E1: Customer Current Total MRC (CAD) | F1: Estimated New Total MRC (CAD) | G1: Number of vHosts | H1: Total Licensable Memory | I1: Total Licensable Cores | J1: Old Per GB RAM Licensing (CAD) | K1: New Per Core Licensing (CAD) | L1: vHosts MRC (CAD) | M1: New vHosts MRC (CAD) | N1: % Change vHosts | O1: % Change Total Customer | P1: Customer Group | Q1: Under Contract | R1: At Risk | S1: Increase Restricted | T1: Increase Effective Date
A2: 7014933 | B2: Transformify Ltd | C2: Jennifer Wilson | D2: NULL | E2: 2083.88 | F2: 2328.844 | G2: 1 | H2: 64 | I2: 16 | J2: 294.4 | K2: 539.36 | L2: 1794.4245 | M2: 2039.3845 | N2: 0.13651173 | O2: 0.11754973 | P2: Not Top 200 | Q2: No | R2: Yes | S2: No | T2: 45791
A3: 7012926 | B3: Currencies Direct Ltd | C3: Jennifer Wilson | D3: NULL | E3: 2789.61 | F3: 4961.7655 | G3: 2 | H3: 128 | I3: 64 | J3: 588.8 | K3: 2760.96 | L3: 2488.893 | M3: 4661.053 | N3: 0.87274142 | O3: 0.77866207 | P3: Not Top 200 | Q3: No | R3: No | S3: No | T3: 45797
A4: 7007654 | B4: Cenovus Energy Inc. | C4: Marko Andjelkovic | D4: NULL | E4: 3390.67 | F4: 5169.23 | G4: 2 | H4: 128 | I4: 64 | J4: 588.8 | K4: 2367.36 | L4: 1852 | M4: 3630.56 | N4: 0.96034557 | O4: 0.5245453 | P4: Not Top 200 | Q4: No | R4: Yes | S4: No | T4: 45791
A5: 7014318 | B5: BCOM 2000 HOLDINGS PTY LTD | C5: Jennifer Wilson | D5: NULL | E5: 3183.86 | F5: 3673.7765 | G5: 1 | H5: 128 | I5: 32 | J5: 588.8 | K5: 1078.72 | L5: 1878.426 | M5: 2368.346 | N5: 0.26081411 | O5: 0.15387628 | P5: Not Top 200 | Q5: No | R5: Yes | S5: No | T5: 45791
A6: 7014317 | B6: eMetrix Systems, LLC | C6: Steve Rioux | D6: NULL | E6: 3086.46 | F6: 3576.3845 | G6: 1 | H6: 128 | I6: 32 | J6: 588.8 | K6: 1078.72 | L6: 1707.454 | M6: 2197.374 | N6: 0.28693013 | O6: 0.15873178 | P6: Not Top 200 | Q6: No | R6: Yes | S6: No | T6: 45791
A7: 5960514 | B7: ViOptix, Inc. - PO # 1357 | C7: Roger Gonzales | D7: NULL | E7: 2054.86 | F7: 2944.1433 | G7: 2 | H7: 64 | I7: 32 | J7: 294.4 | K7: 1183.68 | L7: 1165.7982 | M7: 2055.0782 | N7: 0.76280783 | O7: 0.43276845 | P7: Not Top 200 | Q7: No | R7: Yes | S7: No | T7: 45791
A8: 7002729 | B8: Blue Cow Software | C8: Roger Gonzales | D8: NULL | E8: 4406.99 | F8: 5149.0749 | G8: 1 | H8: 96 | I8: 32 | J8: 441.6 | K8: 1183.68 | L8: 2582.86 | M8: 3324.94 | N8: 0.28730942 | O8: 0.16838685 | P8: Not Top 200 | Q8: No | R8: Yes | S8: No | T8: 45791
A9: 1000343 | B9: Internet Edge Solutions Inc. | C9: Roland Gonzales | D9: NULL | E9: 4903.96 | F9: 6388.12 | G9: 2 | H9: 192 | I9: 64 | J9: 883.2 | K9: 2367.36 | L9: 1851.1 | M9: 3335.26 | N9: 0.80177192 | O9: 0.30264521 | P9: Not Top 200 | Q9: No | R9: Yes | S9: No | T9: 45791
A10: 7010154 | B10: Baring Vostok Capital Partners Limited | C10: Jennifer Wilson | D10: NULL | E10: 4714.05 | F10: 5652.93 | G10: 1 | H10: 96 | I10: 32 | J10: 441.6 | K10: 1380.48 | L10: 3163.05 | M10: 4101.93 | N10: 0.29682743 | O10: 0.19916632 | P10: Top 200 | Q10: No | R10: No | S10: No | T10: 45797
A11: 5573207 | B11: dbridge inc. | C11: Roger Gonzales | D11: NULL | E11: 5492.71 | F11: 7664.8738 | G11: 2 | H11: 128 | I11: 64 | J11: 588.8 | K11: 2760.96 | L11: 2209.9546 | M11: 4382.1146 | N11: 0.98289802 | O11: 0.39546208 | P11: Top 200 | Q11: No | R11: No | S11: No | T11: 45797
A12: 7003351 | B12: ENTREGAS PUNTUALES S DE RL DE CV | C12: Elizabeth Perez | D12: NULL | E12: 1975.52 | F12: 2178.3955 | G12: 2 | H12: 256 | I12: 32 | J12: 1177.6 | K12: 1380.48 | L12: 3115.658 | M12: 3318.538 | N12: 0.065116261 | O12: 0.10269725 | P12: Not Top 200 | Q12: No | R12: No | S12: No | T12: 45797
A13: 7000559 | B13: Arctrieval, Inc | C13: Marko Andjelkovic | D13: NULL | E13: 3022.68 | F13: 3512.5977 | G13: 2 | H13: 128 | I13: 32 | J13: 588.8 | K13: 1078.72 | L13: 1589.084 | M13: 2079.004 | N13: 0.3083034 | O13: 0.16208146 | P13: Not Top 200 | Q13: No | R13: Yes | S13: No | T13: 45791
... A50: 7014572 | B50: Centro Internacional de Mejoramiento de Maíz y Trigo | C50: Elizabeth Perez | D50: NULL | E50: 42920.52 | F50: 42920.521 | G50: 2 | H50: 1024 | I50: 64 | J50: 4710.4 | K50: 4710.4 | L50: 9713.788 | M50: 9713.788 | N50: 0 | O50: 0 | P50: Top 200 | Q50: No | R50: No | S50: No | T50: 45797

Sheet Pivot Table 1
A1: Client name | I1: Old RAM $ CAD | J1: New Ron Core $ Cad | K1: Total HW MRC CAD | L1: Delta of JUST VMWare | M1: % Delta | N1: % Delta of Total | O1: Compatable
A2: {=index('Data from Ocean'!B:B,match(B2,'Data from Ocean'!A:A,0))} -> Internet Edge Solutions Inc. | I2: {=index('Original Spreadsheet'!J:J,match(B2,'Original Spreadsheet'!A:A,0))} -> 883.2 | J2: {=index('Original Spreadsheet'!K:K,match(B2,'Original Spreadsheet'!A:A,0))} -> 2367.36 | K2: {=index('Original Spreadsheet'!E:E,match(B2,'Original Spreadsheet'!A:A,0))} -> 4903.96 | L2: =H2-I2 -> 1484 | M2: =(H2-I2)/I2 -> 1.6802536 | N2: =L2/K2 -> 0.30261258 | O2: {=index('Data from Ocean'!M:M,match(B2,'Data from Ocean'!A:A,0))} -> 7
A3: {=index('Data from Ocean'!B:B,match(B3,'Data from Ocean'!A:A,0))} -> Kinetico | I3: {=index('Original Spreadsheet'!J:J,match(B3,'Original Spreadsheet'!A:A,0))} -> 4121.6 | J3: {=index('Original Spreadsheet'!K:K,match(B3,'Original Spreadsheet'!A:A,0))} -> 5116.16 | K3: {=index('Original Spreadsheet'!E:E,match(B3,'Original Spreadsheet'!A:A,0))} -> 16815.19 | L3: =H3-I3 -> 612.8 | M3: =(H3-I3)/I3 -> 0.14868012 | N3: =L3/K3 -> 0.03644324 | O3: {=index('Data from Ocean'!M:M,match(B3,'Data from Ocean'!A:A,0))} -> 7,8
A4: {=index('Data from Ocean'!B:B,match(B4,'Data from Ocean'!A:A,0))} -> dbridge inc. | I4: {=index('Original Spreadsheet'!J:J,match(B4,'Original Spreadsheet'!A:A,0))} -> 588.8 | J4: {=index('Original Spreadsheet'!K:K,match(B4,'Original Spreadsheet'!A:A,0))} -> 2760.96 | K4: {=index('Original Spreadsheet'!E:E,match(B4,'Original Spreadsheet'!A:A,0))} -> 5492.71 | L4: =H4-I4 -> 594.8 | M4: =(H4-I4)/I4 -> 1.0101902 | N4: =L4/K4 -> 0.10828899 | O4: {=index('Data from Ocean'!M:M,match(B4,'Data from Ocean'!A:A,0))} -> 7,8
A5: {=index('Data from Ocean'!B:B,match(B5,'Data from Ocean'!A:A,0))} -> Nikon Instruments Inc. | I5: {=index('Original Spreadsheet'!J:J,match(B5,'Original Spreadsheet'!A:A,0))} -> 294.4 | J5: {=index('Original Spreadsheet'!K:K,match(B5,'Original Spreadsheet'!A:A,0))} -> 539.36 | K5: {=index('Original Spreadsheet'!E:E,match(B5,'Original Spreadsheet'!A:A,0))} -> 3141.03 | L5: =H5-I5 -> 297.4 | M5: =(H5-I5)/I5 -> 1.0101902 | N5: =L5/K5 -> 0.094682318 | O5: {=index('Data from Ocean'!M:M,match(B5,'Data from Ocean'!A:A,0))} -> 7,8
A6: {=index('Data from Ocean'!B:B,match(B6,'Data from Ocean'!A:A,0))} -> Global Maritime Transportation Services, Inc. | I6: {=index('Original Spreadsheet'!J:J,match(B6,'Original Spreadsheet'!A:A,0))} -> 1766.4 | J6: {=index('Original Spreadsheet'!K:K,match(B6,'Original Spreadsheet'!A:A,0))} -> 2367.36 | K6: {=index('Original Spreadsheet'!E:E,match(B6,'Original Spreadsheet'!A:A,0))} -> 11895.83 | L6: =H6-I6 -> 600.8 | M6: =(H6-I6)/I6 -> 0.34012681 | N6: =L6/K6 -> 0.050505093 | O6: {=index('Data from Ocean'!M:M,match(B6,'Data from Ocean'!A:A,0))} -> 7,8
A7: {=index('Data from Ocean'!B:B,match(B7,'Data from Ocean'!A:A,0))} -> Supplier Solutions | I7: {=index('Original Spreadsheet'!J:J,match(B7,'Original Spreadsheet'!A:A,0))} -> 3532.8 | J7: {=index('Original Spreadsheet'!K:K,match(B7,'Original Spreadsheet'!A:A,0))} -> 3532.8 | K7: {=index('Original Spreadsheet'!E:E,match(B7,'Original Spreadsheet'!A:A,0))} -> 32158.92 | L7: =H7-I7 -> 1201.6 | M7: =(H7-I7)/I7 -> 0.34012681 | N7: =L7/K7 -> 0.037364439 | O7: {=index('Data from Ocean'!M:M,match(B7,'Data from Ocean'!A:A,0))} -> 7,8
A8: {=index('Data from Ocean'!B:B,match(B8,'Data from Ocean'!A:A,0))} -> ViOptix, Inc. - PO # 1357 | I8: {=index('Original Spreadsheet'!J:J,match(B8,'Original Spreadsheet'!A:A,0))} -> 294.4 | J8: {=index('Original Spreadsheet'!K:K,match(B8,'Original Spreadsheet'!A:A,0))} -> 1183.68 | K8: {=index('Original Spreadsheet'!E:E,match(B8,'Original Spreadsheet'!A:A,0))} -> 2054.86 | L8: =H8-I8 -> 889.2 | M8: =(H8-I8)/I8 -> 3.0203804 | N8: =L8/K8 -> 0.43273021 | O8: {=index('Data from Ocean'!M:M,match(B8,'Data from Ocean'!A:A,0))} -> 7,8
A9: {=index('Data from Ocean'!B:B,match(B9,'Data from Ocean'!A:A,0))} -> RepoSystems.Com Inc. | I9: {=index('Original Spreadsheet'!J:J,match(B9,'Original Spreadsheet'!A:A,0))} -> 1766.4 | J9: {=index('Original Spreadsheet'!K:K,match(B9,'Original Spreadsheet'!A:A,0))} -> 2157.44 | K9: {=index('Original Spreadsheet'!E:E,match(B9,'Original Spreadsheet'!A:A,0))} -> 6856.46 | L9: =H9-I9 -> 600.8 | M9: =(H9-I9)/I9 -> 0.34012681 | N9: =L9/K9 -> 0.087625393 | O9: {=index('Data from Ocean'!M:M,match(B9,'Data from Ocean'!A:A,0))} -> 7,8
A10: {=index('Data from Ocean'!B:B,match(B10,'Data from Ocean'!A:A,0))} -> Enidus USA, LLC | I10: {=index('Original Spreadsheet'!J:J,match(B10,'Original Spreadsheet'!A:A,0))} -> 2649.6 | J10: {=index('Original Spreadsheet'!K:K,match(B10,'Original Spreadsheet'!A:A,0))} -> 3551.04 | K10: {=index('Original Spreadsheet'!E:E,match(B10,'Original Spreadsheet'!A:A,0))} -> 24354.83 | L10: =H10-I10 -> 901.2 | M10: =(H10-I10)/I10 -> 0.34012681 | N10: =L10/K10 -> 0.037002927 | O10: {=index('Data from Ocean'!M:M,match(B10,'Data from Ocean'!A:A,0))} -> 7,8
A11: {=index('Data from Ocean'!B:B,match(B11,'Data from Ocean'!A:A,0))} -> Arctrieval, Inc | I11: {=index('Original Spreadsheet'!J:J,match(B11,'Original Spreadsheet'!A:A,0))} -> 588.8 | J11: {=index('Original Spreadsheet'!K:K,match(B11,'Original Spreadsheet'!A:A,0))} -> 1078.72 | K11: {=index('Original Spreadsheet'!E:E,match(B11,'Original Spreadsheet'!A:A,0))} -> 3022.68 | L11: =H11-I11 -> 594.8 | M11: =(H11-I11)/I11 -> 1.0101902 | N11: =L11/K11 -> 0.19677902 | O11: {=index('Data from Ocean'!M:M,match(B11,'Data from Ocean'!A:A,0))} -> 7,8
A12: {=index('Data from Ocean'!B:B,match(B12,'Data from Ocean'!A:A,0))} -> Engage People Inc. | I12: {=index('Original Spreadsheet'!J:J,match(B12,'Original Spreadsheet'!A:A,0))} -> #N/A | J12: {=index('Original Spreadsheet'!K:K,match(B12,'Original Spreadsheet'!A:A,0))} -> #N/A | K12: {=index('Original Spreadsheet'!E:E,match(B12,'Original Spreadsheet'!A:A,0))} -> #N/A | L12: =H12-I12 -> #N/A | M12: =(H12-I12)/I12 -> #N/A | N12: =L12/K12 -> #N/A | O12: {=index('Data from Ocean'!M:M,match(B12,'Data from Ocean'!A:A,0))} -> 7,8
A13: {=index('Data from Ocean'!B:B,match(B13,'Data from Ocean'!A:A,0))} -> Adam Matthew Digital | I13: {=index('Original Spreadsheet'!J:J,match(B13,'Original Spreadsheet'!A:A,0))} -> 2649.6 | J13: {=index('Original Spreadsheet'!K:K,match(B13,'Original Spreadsheet'!A:A,0))} -> 3551.04 | K13: {=index('Original Spreadsheet'!E:E,match(B13,'Original Spreadsheet'!A:A,0))} -> 31776.35 | L13: =H13-I13 -> 901.2 | M13: =(H13-I13)/I13 -> 0.34012681 | N13: =L13/K13 -> 0.028360715 | O13: {=index('Data from Ocean'!M:M,match(B13,'Data from Ocean'!A:A,0))} -> 7,8
... A46: {=index('Data from Ocean'!B:B,match(B46,'Data from Ocean'!A:A,0))} -> Alaya Care Inc | I46: {=index('Original Spreadsheet'!J:J,match(B46,'Original Spreadsheet'!A:A,0))} -> 883.2 | J46: {=index('Original Spreadsheet'!K:K,match(B46,'Original Spreadsheet'!A:A,0))} -> 2760.96 | K46: {=index('Original Spreadsheet'!E:E,match(B46,'Original Spreadsheet'!A:A,0))} -> 6574.94 | L46: =H46-I46 -> 1484 | M46: =(H46-I46)/I46 -> 1.6802536 | N46: =L46/K46 -> 0.22570548 | O46: {=index('Data from Ocean'!M:M,match(B46,'Data from Ocean'!A:A,0))} -> 7,8
L47: =H47-I47 -> 138185.44 | N47: =L47/K47 -> #DIV/0!
